LABORATORIO-3/TABLA_03POS/tabla_03p.v
//---------------------------
//GABRIEL ALEXANDER FONG PENAGOS
//CARNET 19722
//ELECTRONICA DIGITAL
//LABORATORIO 03
//EJERCICIO TABLA 03 VERSION POS

module tabla_03p();                                         //GENERAMOS EL MODULO

  wire w1,w2,w3,w4,w5,w6,w7,w8,w9,nA,nB,nC,nD,sal;         //NOMBRAMOS NUESTROS CABLES QUE SALDRAN DE LAS AND, LAS NEGACIONES DE NUESTRA VARIABLES BINARIAS Y LA SALIDA
  reg A, B, C, D;                                          //NOMBRAMOS NUESTRAS ENTRADAS COMO REGISTROS

//COMPUERTAS

//COMPUERTAS NOT
  not U1(nA,A);
  not U2(nB,B);
  not U3(nC,C);
  not U4(nD,D);

//COMPUERTAS OR
  or  U5(w1,A,nB,C,D);
  or  U6(w2,A,nB,C,nD);
  or  U7(w3,A,nB,nC,D);
  or  U8(w4,A,nB,nC,nD);
  or  U9(w5,nA,B,C,nD);
  or  U10(w6,nA,B,nC,nD);
  or  U11(w7,nA,nB,C,D);
  or  U12(w8,nA,nB,C,nD);
  or  U13(w9,nA,nB,nC,nD);

//COMPUERTA AND
  and U14(sal,w1,w2,w3,w4,w5,w6,w7,w8,w9);

  initial begin                                               //INICIAMOS LA SIMULACION
    $display("POS A B C D|Y");                                //IMPRIMIMOS EN LA TERMINAL
    $display("---------|-");
    $monitor("%b %b %b %B| %b", A, B, C, D, sal);             //MUESTRA LOS VALORES DE A B C D y LA SALIDA
    A = 0; B = 0; C = 0; D = 0;                               //CAMBIAMOS LOS VALORES
    #1 A = 0; B = 0; C = 0; D = 1;                            //COLOCAMOS UN INTERVALO DE TIEMPO PARA CAMBIAR LOS VALORES DE LAS ENTRADAS
    #1 A = 0; B = 0; C = 1; D = 0;
    #1 A = 0; B = 0; C = 1; D = 1;
    #1 A = 0; B = 1; C = 0; D = 0;
    #1 A = 0; B = 1; C = 0; D = 1;
    #1 A = 0; B = 1; C = 1; D = 0;
    #1 A = 0; B = 1; C = 1; D = 1;
    #1 A = 1; B = 0; C = 0; D = 0;
    #1 A = 1; B = 0; C = 0; D = 1;
    #1 A = 1; B = 0; C = 1; D = 0;
    #1 A = 1; B = 0; C = 1; D = 1;
    #1 A = 1; B = 1; C = 0; D = 0;
    #1 A = 1; B = 1; C = 0; D = 1;
    #1 A = 1; B = 1; C = 1; D = 0;
    #1 A = 1; B = 1; C = 1; D = 1;
    #1 $finish;                                                 //FINALIZAMOS LA SIMULACION
  end

  initial                                                      //INICIAMOS PARA MOSTRAR LA SIMULACION EN GTK WAVE
    begin
      $dumpfile("tabla_03p_tb.vcd");                           //COLOCAMOS LA EXTENSION DEL ARCHIVO _tb Y COLOCAMOS .vcd PARA MOSTRAR EN GTK WAVE
      $dumpvars(0,tabla_03p);                                  //TOMAMOS LOS VALORES DEL ARCHIVO
    end

  endmodule                                       //TERMINAMOS EL MODULO

LABORATORIO-3/TABLA_03POS/tabla_03p_tb.vcd
$date
	Fri Jul 31 23:27:08 2020
$end
$version
	Icarus Verilog
$end
$timescale
	1ps
$end
$scope module tabla_03p $end
$var wire 1 ! nA $end
$var wire 1 " nB $end
$var wire 1 # nC $end
$var wire 1 $ nD $end
$var wire 1 % sal $end
$var wire 1 & w1 $end
$var wire 1 ' w2 $end
$var wire 1 ( w3 $end
$var wire 1 ) w4 $end
$var wire 1 * w5 $end
$var wire 1 + w6 $end
$var wire 1 , w7 $end
$var wire 1 - w8 $end
$var wire 1 . w9 $end
$var reg 1 / A $end
$var reg 1 0 B $end
$var reg 1 1 C $end
$var reg 1 2 D $end
$upscope $end
$enddefinitions $end
#0
$dumpvars
02
01
00
0/
1.
1-
1,
1+
1*
1)
1(
1'
1&
1%
1$
1#
1"
1!
$end
#1
0$
12
#2
1$
0#
02
11
#3
0$
12
#4
0%
1$
1'
0&
1#
0"
02
01
10
#5
0'
1&
0$
12
#6
0(
1$
1'
0#
02
11
#7
0)
1(
0$
12
#8
1%
1$
1#
1+
1*
1"
1)
0!
02
01
00
1/
#9
0%
0*
0$
12
#10
1%
1$
1*
0#
02
11
#11
0%
0+
0$
12
#12
1$
1-
0,
1#
1+
0"
02
01
10
#13
0-
1,
0$
12
#14
1%
1$
1-
0#
02
11
#15
0%
0.
0$
12
