LABORATORIO-3/TABLA_04SOP/tabla_04s.v
//---------------------------
//GABRIEL ALEXANDER FONG PENAGOS
//CARNET 19722
//ELECTRONICA DIGITAL
//LABORATORIO 03
//EJERCICIO TABLA 04 VERSION SOP

module tabla_04s();                                         //GENERAMOS EL MODULO

  wire w1,w2,w3,w4,w5,w6,w7,nA,nB,nC,nD,sal;                //NOMBRAMOS NUESTROS CABLES QUE SALDRAN DE LAS AND, LAS NEGACIONES DE NUESTRA VARIABLES BINARIAS Y LA SALIDA
  reg A, B, C, D;                                          //NOMBRAMOS NUESTRAS ENTRADAS COMO REGISTROS

//COMPUERTAS

//COMPUERTAS NOT
  not U1(nA,A);
  not U2(nB,B);
  not U3(nC,C);
  not U4(nD,D);

//COMPUERTAS AND
  and U5(w1,nA,nB,nC,nD);
  and U6(w2,nA,nB,C,nD);
  and U7(w3,nA,nB,C,D);
  and U8(w4,nA,B,C,nD);
  and U9(w5,nA,B,C,D);
  and U10(w6,A,nB,nC,nD);
  and U11(w7,A,nB,C,nD);

//COMPUERTA OR
  or  U12(sal,w1,w2,w3,w4,w5,w6,w7);

  initial begin                                               //INICIAMOS LA SIMULACION
    $display("SOP A B C D|Y");                                //IMPRIMIMOS EN LA TERMINAL
    $display("---------|-");
    $monitor("%b %b %b %B| %b", A, B, C, D, sal);             //MUESTRA LOS VALORES DE A B C D y LA SALIDA
    A = 0; B = 0; C = 0; D = 0;                               //CAMBIAMOS LOS VALORES
    #1 A = 0; B = 0; C = 0; D = 1;                            //COLOCAMOS UN INTERVALO DE TIEMPO PARA CAMBIAR LOS VALORES DE LAS ENTRADAS
    #1 A = 0; B = 0; C = 1; D = 0;
    #1 A = 0; B = 0; C = 1; D = 1;
    #1 A = 0; B = 1; C = 0; D = 0;
    #1 A = 0; B = 1; C = 0; D = 1;
    #1 A = 0; B = 1; C = 1; D = 0;
    #1 A = 0; B = 1; C = 1; D = 1;
    #1 A = 1; B = 0; C = 0; D = 0;
    #1 A = 1; B = 0; C = 0; D = 1;
    #1 A = 1; B = 0; C = 1; D = 0;
    #1 A = 1; B = 0; C = 1; D = 1;
    #1 A = 1; B = 1; C = 0; D = 0;
    #1 A = 1; B = 1; C = 0; D = 1;
    #1 A = 1; B = 1; C = 1; D = 0;
    #1 A = 1; B = 1; C = 1; D = 1;
    #1 $finish;                                                 //FINALIZAMOS LA SIMULACION
  end

  initial                                                      //INICIAMOS PARA MOSTRAR LA SIMULACION EN GTK WAVE
    begin
      $dumpfile("tabla_04s_tb.vcd");                           //COLOCAMOS LA EXTENSION DEL ARCHIVO _tb Y COLOCAMOS .vcd PARA MOSTRAR EN GTK WAVE
      $dumpvars(0,tabla_04s);                                  //TOMAMOS LOS VALORES DEL ARCHIVO
    end

  endmodule                                       //TERMINAMOS EL MODULO

LABORATORIO-3/TABLA_04SOP/tabla_04s_tb.vcd
$date
	Fri Jul 31 23:33:15 2020
$end
$version
	Icarus Verilog
$end
$timescale
	1ps
$end
$scope module tabla_04s $end
$var wire 1 ! nA $end
$var wire 1 " nB $end
$var wire 1 # nC $end
$var wire 1 $ nD $end
$var wire 1 % sal $end
$var wire 1 & w1 $end
$var wire 1 ' w2 $end
$var wire 1 ( w3 $end
$var wire 1 ) w4 $end
$var wire 1 * w5 $end
$var wire 1 + w6 $end
$var wire 1 , w7 $end
$var reg 1 - A $end
$var reg 1 . B $end
$var reg 1 / C $end
$var reg 1 0 D $end
$upscope $end
$enddefinitions $end
#0
$dumpvars
00
0/
0.
0-
0,
0+
0*
0)
0(
0'
1&
1%
1$
1#
1"
1!
$end
#1
0%
0&
0$
10
#2
1%
1'
1$
0#
00
1/
#3
0'
1(
0$
10
#4
0%
1$
0(
1#
0"
00
0/
1.
#5
0$
10
#6
1%
1)
1$
0#
00
1/
#7
0)
1*
0$
10
#8
1+
1$
1#
0*
1"
0!
00
0/
0.
1-
#9
0%
0+
0$
10
#10
1%
1,
1$
0#
00
1/
#11
0%
0,
0$
10
#12
1$
1#
0"
00
0/
1.
#13
0$
10
#14
1$
0#
00
1/
#15
0$
10
