LABORATORIO-10/CODIGO2/LAB10D.v
//LABORATORIO 10
//ELECTRONICA DIGITAL I
//GABRIEL ALEXANDER FONG PENAGOS 19722
//EJERCICO #2

//BUFFER TRIESTADO DE 4 BITS. 1 PARA LA ENTRADA B DE LA ALU (DATA BUS), OTRO PARA LA SALIDA DE LA ALU
module BUSDRIVER (input wire [3:0]D,
                input wire enable,
                output wire [3:0]Y);
  assign Y = enable ? D : 4'bz;
 //si enable = 1 deja pasar el dato de D, sino en alta impedancia

endmodule // BUSDRIVER

module ACCUMULATOR(input wire clk, reset, enable,
              input wire [3:0]ALUS,
              output reg [3:0]ACCU);
    always @ ( posedge clk, posedge reset ) begin
      if (reset) begin
        ACCU<= 4'b0;
      end
      else if (enable) begin //SI EL ENABLE == 1 DEJA PASAR EL VALOR DE D A LA SALIDA Q
        ACCU<= ALUS; //LOS 4 BITS DE LA SALIDA DE LA ALU SE DIRIGEN HACIA EL ACUMULADOR
      end
    end
endmodule

module ALU (input wire [3:0]ACCU,DATA_BUS, //ACCU = A  VIENE DEL ACUMULADOR  DATA_BUS = B VIENE DEL BUFFER DATA_BUS
            input wire [2:0]F,      //SELECTOR DE LAS OPERACIONES
            output wire [3:0]OUT,
            output wire CARRY,ZERO); //SALIDA

  reg  [4:0]OUT5;
  always @ (ACCU,DATA_BUS,F ) begin
    case (F)
      3'b000: OUT5 <= ACCU;
      3'b001: OUT5 <= ACCU - DATA_BUS;
      3'b010: OUT5 <= DATA_BUS;
      3'b011: OUT5 <= ACCU + DATA_BUS;
      3'b100: OUT5 <= (ACCU ~| DATA_BUS);
      default: OUT5 <= 5'b00000;
    endcase
  end
  assign OUT = OUT5[3:0];
  assign CARRY = OUT5[4];
  assign ZERO = (OUT5 == 5'b00000) ? 1:0;


endmodule // ALU

module PARTE2 (input wire clk, resetA,enableA, enableB1,enableB2,
               input wire [2:0]F,
               input wire [3:0]OPRND,
               output wire[3:0]OUT,
               output wire [3:0]DATA, ALUY, ACU,
               output wire CARRY, ZERO);
  wire [3:0]DATA_BUS, ALUS, ACCU;
  BUSDRIVER U1(OPRND, enableB1,DATA_BUS);
  BUSDRIVER U2(ALUS, enableB2, OUT);
  ACCUMULATOR U3(clk,resetA, enableA, ALUS,ACCU);
  ALU U4(ACCU, DATA_BUS, F,ALUS,CARRY, ZERO );
  assign DATA = DATA_BUS;
  assign ALUY = ALUS;
  assign ACU = ACCU;

endmodule // PARTE2

LABORATORIO-10/CODIGO2/LAB10D_tb.v
//LABORATORIO 10
//ELECTRONICA DIGITAL I
//GABRIEL ALEXANDER FONG PENAGOS 19722
//EJERCICO 2
//TESTBENCH

module testbench ();
reg clk, resetA, enableB1, enableB2, enableA;
reg [3:0]OPRND;
reg [2:0]F;
wire [3:0] OUT, DATA, ALUY, ACU;
wire CARRY, ZERO;


always begin //REALIZAMOS EL RELOJ Y QUE CAMBIE CADA UNIDAD DE TIEMPO
  clk <= 1; #1 clk <= ~clk; #1;
end

PARTE2 U1(clk, resetA,enableA, enableB1, enableB2,F, OPRND,OUT, DATA, ALUY, ACU, CARRY, ZERO);

initial begin
resetA = 1;enableB1= 1;enableB2 = 1; F = 3'b000; enableA = 1; //RESETEAMOS ENCENDEMOS EL ENABLE, la bandera del load la apagamos
#1
$display("\n");
$display(" EJERCICIO 2");
$display("CLK   RESETA \t ENABLEB1   ENABLEB2 \t F  \t OPRND \t OUT \t DATA \t SALIDA  ACCU \t CARRY \t ZERO ");
$display("--------------------------------------------------------------------------------------------------------------");
$monitor("  %b \t %b\t   %b \t\t %b \t %b \t  %b \t %b \t %b \t %b \t %b \t %b \t %b  ", clk, resetA, enableB1,enableB2,F,OPRND,OUT,DATA, ALUY, ACU, CARRY, ZERO);
#1 resetA = 0;
#2 OPRND = 4'b1010;
#2 F = 3'b010;
#2 F = 3'b001;
#2 F = 3'b011;
#2 F = 3'b100; enableB2 = 0; OPRND = 4'b1111;
#2 F = 3'b010;
#2 enableB2 = 1;
#2 F = 3'b000;
#2 enableB1 = 0;OPRND = 4'b0001;
#2 F = 3'b010;
#2 enableB1 = 1;
#2 $finish;
end

initial begin                                                                 //INICIAMOS PARA COLOCAR LOS DATOS EN GTK WAVE
      $dumpfile("LAB10D_tb.vcd");
      $dumpvars(0, testbench);
    end

endmodule // testbench

LABORATORIO-10/CODIGO2/LAB10D_tb.vcd
$date
	Fri Nov 06 23:54:58 2020
$end
$version
	Icarus Verilog
$end
$timescale
	1ps
$end
$scope module testbench $end
$var wire 1 ! ZERO $end
$var wire 4 " OUT [3:0] $end
$var wire 4 # DATA [3:0] $end
$var wire 1 $ CARRY $end
$var wire 4 % ALUY [3:0] $end
$var wire 4 & ACU [3:0] $end
$var reg 3 ' F [2:0] $end
$var reg 4 ( OPRND [3:0] $end
$var reg 1 ) clk $end
$var reg 1 * enableA $end
$var reg 1 + enableB1 $end
$var reg 1 , enableB2 $end
$var reg 1 - resetA $end
$scope module U1 $end
$var wire 4 . ACU [3:0] $end
$var wire 4 / ALUY [3:0] $end
$var wire 4 0 DATA [3:0] $end
$var wire 3 1 F [2:0] $end
$var wire 4 2 OPRND [3:0] $end
$var wire 1 ) clk $end
$var wire 1 * enableA $end
$var wire 1 + enableB1 $end
$var wire 1 , enableB2 $end
$var wire 1 - resetA $end
$var wire 1 ! ZERO $end
$var wire 4 3 OUT [3:0] $end
$var wire 4 4 DATA_BUS [3:0] $end
$var wire 1 $ CARRY $end
$var wire 4 5 ALUS [3:0] $end
$var wire 4 6 ACCU [3:0] $end
$scope module U1 $end
$var wire 4 7 D [3:0] $end
$var wire 1 + enable $end
$var wire 4 8 Y [3:0] $end
$upscope $end
$scope module U2 $end
$var wire 1 , enable $end
$var wire 4 9 Y [3:0] $end
$var wire 4 : D [3:0] $end
$upscope $end
$scope module U3 $end
$var wire 1 ) clk $end
$var wire 1 * enable $end
$var wire 1 - reset $end
$var wire 4 ; ALUS [3:0] $end
$var reg 4 < ACCU [3:0] $end
$upscope $end
$scope module U4 $end
$var wire 4 = ACCU [3:0] $end
$var wire 4 > DATA_BUS [3:0] $end
$var wire 3 ? F [2:0] $end
$var wire 1 ! ZERO $end
$var wire 4 @ OUT [3:0] $end
$var wire 1 $ CARRY $end
$var reg 5 A OUT5 [4:0] $end
$upscope $end
$upscope $end
$upscope $end
$enddefinitions $end
#0
$dumpvars
b0 A
b0 @
b0 ?
bx >
b0 =
b0 <
b0 ;
b0 :
b0 9
bx 8
bx 7
b0 6
b0 5
bx 4
b0 3
bx 2
b0 1
bx 0
b0 /
b0 .
1-
1,
1+
1*
1)
bx (
b0 '
b0 &
b0 %
0$
bx #
b0 "
1!
$end
#1
0)
#2
1)
0-
#3
0)
#4
1)
b1010 #
b1010 0
b1010 4
b1010 8
b1010 >
b1010 (
b1010 2
b1010 7
#5
0)
#6
b1010 "
b1010 3
b1010 9
0!
b1010 %
b1010 /
b1010 5
b1010 :
b1010 ;
b1010 @
b1010 A
1)
b10 '
b10 1
b10 ?
#7
0)
#8
1!
b1010 &
b1010 .
b1010 6
b1010 <
b1010 =
b0 "
b0 3
b0 9
b0 %
b0 /
b0 5
b0 :
b0 ;
b0 @
0$
b0 A
1)
b1 '
b1 1
b1 ?
#9
0)
#10
b0 &
b0 .
b0 6
b0 <
b0 =
b1010 "
b1010 3
b1010 9
0!
b1010 %
b1010 /
b1010 5
b1010 :
b1010 ;
b1010 @
0$
b1010 A
1)
b11 '
b11 1
b11 ?
#11
0)
#12
b1010 &
b1010 .
b1010 6
b1010 <
b1010 =
b0 %
b0 /
b0 5
b0 :
b0 ;
b0 @
1$
b10000 A
1)
b1111 #
b1111 0
b1111 4
b1111 8
b1111 >
bz "
bz 3
bz 9
b1111 (
b1111 2
b1111 7
0,
b100 '
b100 1
b100 ?
#13
0)
#14
b0 &
b0 .
b0 6
b0 <
b0 =
b1111 %
b1111 /
b1111 5
b1111 :
b1111 ;
b1111 @
0$
b1111 A
1)
b10 '
b10 1
b10 ?
#15
0)
#16
b1111 &
b1111 .
b1111 6
b1111 <
b1111 =
1)
b1111 "
b1111 3
b1111 9
1,
#17
0)
#18
1)
b0 '
b0 1
b0 ?
#19
0)
#20
1)
bz #
bz 0
bz 4
bz 8
bz >
b1 (
b1 2
b1 7
0+
#21
0)
#22
bz "
bz 3
bz 9
x!
bz %
bz /
bz 5
bz :
bz ;
bz @
b0zzzz A
1)
b10 '
b10 1
b10 ?
#23
0)
#24
bz &
bz .
bz 6
bz <
bz =
b1 "
b1 3
b1 9
0!
b1 %
b1 /
b1 5
b1 :
b1 ;
b1 @
b1 A
1)
b1 #
b1 0
b1 4
b1 8
b1 >
1+
#25
0)
#26
b1 &
b1 .
b1 6
b1 <
b1 =
1)
