LABORATORIO-5/LAB5/MUX.v




module MUX2_1(input wire A, B, C, output wire Y); //A es el selector, B Y C SON INPUTS

  assign Y = A?C:B;

endmodule

module MUX4_1(input wire  A, B, C, D, input wire[1:0]S, output wire Y); // S PUEDE SER 1 O 0, SE AGREGA EL VALOR ADENTRO DE CORCHETES

  wire OUT1, OUT2;

  MUX2_1 mux1(S[0], A, B, OUT1);
  MUX2_1 mux2(S[0], C, D, OUT2);
  MUX2_1 mux3(S[1], OUT1, OUT2, Y);

endmodule

module MUX8_1(input wire A, B, C, D, E, F, G, H, input wire [2:0] S, output wire Y); // S PUEDE SER 2, 1, 0

  wire OUT1, OUT2;

  MUX4_1 mux1(A, B, C, D, S[1:0], OUT1);
  MUX4_1 mux2(E, F, G, H, S[1:0], OUT2);
  MUX2_1 mux3(S[2], OUT1, OUT2, Y);

endmodule

module t1_mux2_1(input wire A, B, C, output wire Y); // TABLA 1 CON MUX 2:1 A ES SELECTOR

  wire RES1, RES2;
  assign RES1 = (B^C);                              //REALIZAMOS XOR PARA OBTENER LOS VALORES CUANDO A = 0
  assign RES2 = ~(B^C);                             //REALIZAMOS XNOR PARA OBTENER LOS VALORES CUANDO A = 1

  MUX2_1 U1(A, RES1, RES2, Y);

endmodule

module t1_mux4_1(input wire A, B, C, output wire Y);
  wire [1:0]S;
  assign S[0] = B;
  assign S[1] = A;
  MUX4_1 U2(C, ~C, ~C, C,S[1:0], Y);
endmodule

module t1_mux8_1(input wire A, B, C, GND, VCC, output wire Y);
  wire [2:0]S;
  assign S[0] = C;
  assign S[1] = B;
  assign S[2] = A;
  MUX8_1 U3(GND, VCC, VCC, GND, VCC, GND, GND, VCC, S[2:0], Y);
endmodule

module t2_mux2_1(input wire A, B, C, output wire Y);

  wire RES1, RES2;
  assign RES1 = ~(B | C);
  assign RES2 = ~(B & C);
  MUX2_1 U3(A, RES1, RES2, Y);
endmodule

module t2_mux4_1(input wire A, B, C, GND, output wire Y);

  wire [1:0]S;
  assign S[0] = B;
  assign S[1] = A;
  MUX4_1 U5(~C, GND, C, ~C, S[1:0], Y);
endmodule

module t2_mux8_1(input wire A, B, C, GND, VCC, output wire Y);
  wire [2:0]S;
  assign S[0] = C;
  assign S[1] = B;
  assign S[2] = A;
  MUX8_1 U6(VCC, GND, GND, GND, GND, VCC, VCC, GND, S[2:0], Y);
endmodule

LABORATORIO-5/LAB5/MUX_tb.v


module testbench ();

  wire GND;
  wire VCC;
  assign GND = 0;
  assign VCC = 1;
  reg s1, in1B, in1C;
  reg s2, s3, in2C;
  reg s4, s5, s6;
  reg s7, in4B, in4C;
  reg s8, s9, in5C;
  reg s10, s11, s12;
  wire out1, out2, out3, out4, out5, out6;

  t1_mux2_1 U1(s1, in1B, in1C, out1);
  t1_mux4_1 U2(s2, s3, in2C, out2);
  t1_mux8_1 U3(s4, s5, s6, GND, VCC, out3);
  t2_mux2_1 U4(s7, in4B, in4C, out4);
  t2_mux4_1 U5(s8, s9, in5C, GND, out5);
  t2_mux8_1 U6(s10, s11, s12, GND, VCC, out6);


  initial begin
  #1
  $display("\n");
  $display(" TABLA 1 MUX 2:1 ");
  $display("A FUNCIONA COMO SELECTOR");
  $display("A B C | Y1");
  $display("------|---");
  $monitor("%b %b %b | %b ", s1, in1B, in1C, out1);
     s1 = 0; in1B = 0; in1C = 0;
  #1 s1 = 0; in1B = 0; in1C = 1;
  #1 s1 = 0; in1B = 1; in1C = 0;
  #1 s1 = 0; in1B = 1; in1C = 1;
  #1 s1 = 1; in1B = 0; in1C = 0;
  #1 s1 = 1; in1B = 0; in1C = 1;
  #1 s1 = 1; in1B = 1; in1C = 0;
  #1 s1 = 1; in1B = 1; in1C = 1;
  end

  initial begin
  #9
  $display("\n");
  $display(" TABLA 1 MUX 4:1 ");
  $display("A y B FUNCIONA COMO SELECTOR");
  $display("A B C | Y2");
  $display("------|---");
  $monitor("%b %b %b | %b ", s2, s3, in2C, out2); //selector s2 = A, s3 = B
     s2 = 0; s3 = 0; in2C = 0;
  #1 s2 = 0; s3 = 0; in2C = 1;
  #1 s2 = 0; s3 = 1; in2C = 0;
  #1 s2 = 0; s3 = 1; in2C = 1;
  #1 s2 = 1; s3 = 0; in2C = 0;
  #1 s2 = 1; s3 = 0; in2C = 1;
  #1 s2 = 1; s3 = 1; in2C = 0;
  #1 s2 = 1; s3 = 1; in2C = 1;
  end

  initial begin
  #17
  $display("\n");
  $display(" TABLA 1 MUX 8:1 ");
  $display("A,B y C FUNCIONA COMO SELECTOR");
  $display("A B C | Y3");
  $display("------|---");
  $monitor("%b %b %b | %b ", s4, s5, s6, out3); //selector s4 = A, s5 = B, s6 = C
     s4 = 0; s5 = 0; s6 = 0;
  #1 s4 = 0; s5 = 0; s6 = 1;
  #1 s4 = 0; s5 = 1; s6 = 0;
  #1 s4 = 0; s5 = 1; s6 = 1;
  #1 s4 = 1; s5 = 0; s6 = 0;
  #1 s4 = 1; s5 = 0; s6 = 1;
  #1 s4 = 1; s5 = 1; s6 = 0;
  #1 s4 = 1; s5 = 1; s6 = 1;
  end

  initial begin
  #25
  $display("\n");
  $display(" TABLA 2 MUX 2:1 ");
  $display("A FUNCIONA COMO SELECTOR");
  $display("A B C | Y4");
  $display("------|---");
  $monitor("%b %b %b | %b ", s7, in4B, in4C, out4);
     s7 = 0; in4B = 0; in4C = 0;
  #1 s7 = 0; in4B = 0; in4C = 1;
  #1 s7 = 0; in4B = 1; in4C = 0;
  #1 s7 = 0; in4B = 1; in4C = 1;
  #1 s7 = 1; in4B = 0; in4C = 0;
  #1 s7 = 1; in4B = 0; in4C = 1;
  #1 s7 = 1; in4B = 1; in4C = 0;
  #1 s7 = 1; in4B = 1; in4C = 1;
  end

  initial begin
  #33
  $display("\n");
  $display(" TABLA 2 MUX 4:1 ");
  $display("A y B FUNCIONA COMO SELECTOR");
  $display("A B C | Y2");
  $display("------|---");
  $monitor("%b %b %b | %b ", s8, s9, in5C, out5); //selector s7 = A, s8 = B
     s8 = 0; s9 = 0; in5C = 0;
  #1 s8 = 0; s9 = 0; in5C = 1;
  #1 s8 = 0; s9 = 1; in5C = 0;
  #1 s8 = 0; s9 = 1; in5C = 1;
  #1 s8 = 1; s9 = 0; in5C = 0;
  #1 s8 = 1; s9 = 0; in5C = 1;
  #1 s8 = 1; s9 = 1; in5C = 0;
  #1 s8 = 1; s9 = 1; in5C = 1;
  end

  initial begin
  #43
  $display("\n");
  $display(" TABLA 1 MUX 8:1 ");
  $display("A,B y C FUNCIONA COMO SELECTOR");
  $display("A B C | Y3");
  $display("------|---");
  $monitor("%b %b %b | %b ", s10, s11, s12, out6); //selector s4 = A, s5 = B, s6 = C
     s10 = 0; s11 = 0; s12 = 0;
  #1 s10 = 0; s11 = 0; s12 = 1;
  #1 s10 = 0; s11 = 1; s12 = 0;
  #1 s10 = 0; s11 = 1; s12 = 1;
  #1 s10 = 1; s11 = 0; s12 = 0;
  #1 s10 = 1; s11 = 0; s12 = 1;
  #1 s10 = 1; s11 = 1; s12 = 0;
  #1 s10 = 1; s11 = 1; s12 = 1;
  end

  initial begin                                                               //INICIAMOS PARA COLOCAR LOS DATOS EN GTK WAVE
        $dumpfile("MUX_tb.vcd");
        $dumpvars(0, testbench);
      end

endmodule

LABORATORIO-5/LAB5/MUX_tb.vcd
$date
	Sat Aug 15 22:47:36 2020
$end
$version
	Icarus Verilog
$end
$timescale
	1ps
$end
$scope module testbench $end
$var wire 1 ! GND $end
$var wire 1 " VCC $end
$var wire 1 # out6 $end
$var wire 1 $ out5 $end
$var wire 1 % out4 $end
$var wire 1 & out3 $end
$var wire 1 ' out2 $end
$var wire 1 ( out1 $end
$var reg 1 ) in1B $end
$var reg 1 * in1C $end
$var reg 1 + in2C $end
$var reg 1 , in4B $end
$var reg 1 - in4C $end
$var reg 1 . in5C $end
$var reg 1 / s1 $end
$var reg 1 0 s10 $end
$var reg 1 1 s11 $end
$var reg 1 2 s12 $end
$var reg 1 3 s2 $end
$var reg 1 4 s3 $end
$var reg 1 5 s4 $end
$var reg 1 6 s5 $end
$var reg 1 7 s6 $end
$var reg 1 8 s7 $end
$var reg 1 9 s8 $end
$var reg 1 : s9 $end
$scope module U1 $end
$var wire 1 / A $end
$var wire 1 ) B $end
$var wire 1 * C $end
$var wire 1 ; RES1 $end
$var wire 1 < RES2 $end
$var wire 1 ( Y $end
$scope module U1 $end
$var wire 1 / A $end
$var wire 1 ; B $end
$var wire 1 < C $end
$var wire 1 ( Y $end
$upscope $end
$upscope $end
$scope module U2 $end
$var wire 1 3 A $end
$var wire 1 4 B $end
$var wire 1 + C $end
$var wire 1 ' Y $end
$var wire 2 = S [1:0] $end
$scope module U2 $end
$var wire 1 + A $end
$var wire 1 > B $end
$var wire 1 ? C $end
$var wire 1 + D $end
$var wire 2 @ S [1:0] $end
$var wire 1 ' Y $end
$var wire 1 A OUT2 $end
$var wire 1 B OUT1 $end
$scope module mux1 $end
$var wire 1 C A $end
$var wire 1 + B $end
$var wire 1 > C $end
$var wire 1 B Y $end
$upscope $end
$scope module mux2 $end
$var wire 1 D A $end
$var wire 1 ? B $end
$var wire 1 + C $end
$var wire 1 A Y $end
$upscope $end
$scope module mux3 $end
$var wire 1 E A $end
$var wire 1 B B $end
$var wire 1 A C $end
$var wire 1 ' Y $end
$upscope $end
$upscope $end
$upscope $end
$scope module U3 $end
$var wire 1 5 A $end
$var wire 1 6 B $end
$var wire 1 7 C $end
$var wire 1 ! GND $end
$var wire 1 " VCC $end
$var wire 1 & Y $end
$var wire 3 F S [2:0] $end
$scope module U3 $end
$var wire 1 ! A $end
$var wire 1 " B $end
$var wire 1 " C $end
$var wire 1 ! D $end
$var wire 1 " E $end
$var wire 1 ! F $end
$var wire 1 ! G $end
$var wire 1 " H $end
$var wire 3 G S [2:0] $end
$var wire 1 & Y $end
$var wire 1 H OUT2 $end
$var wire 1 I OUT1 $end
$scope module mux1 $end
$var wire 1 ! A $end
$var wire 1 " B $end
$var wire 1 " C $end
$var wire 1 ! D $end
$var wire 2 J S [1:0] $end
$var wire 1 I Y $end
$var wire 1 K OUT2 $end
$var wire 1 L OUT1 $end
$scope module mux1 $end
$var wire 1 M A $end
$var wire 1 ! B $end
$var wire 1 " C $end
$var wire 1 L Y $end
$upscope $end
$scope module mux2 $end
$var wire 1 N A $end
$var wire 1 " B $end
$var wire 1 ! C $end
$var wire 1 K Y $end
$upscope $end
$scope module mux3 $end
$var wire 1 O A $end
$var wire 1 L B $end
$var wire 1 K C $end
$var wire 1 I Y $end
$upscope $end
$upscope $end
$scope module mux2 $end
$var wire 1 " A $end
$var wire 1 ! B $end
$var wire 1 ! C $end
$var wire 1 " D $end
$var wire 2 P S [1:0] $end
$var wire 1 H Y $end
$var wire 1 Q OUT2 $end
$var wire 1 R OUT1 $end
$scope module mux1 $end
$var wire 1 S A $end
$var wire 1 " B $end
$var wire 1 ! C $end
$var wire 1 R Y $end
$upscope $end
$scope module mux2 $end
$var wire 1 T A $end
$var wire 1 ! B $end
$var wire 1 " C $end
$var wire 1 Q Y $end
$upscope $end
$scope module mux3 $end
$var wire 1 U A $end
$var wire 1 R B $end
$var wire 1 Q C $end
$var wire 1 H Y $end
$upscope $end
$upscope $end
$scope module mux3 $end
$var wire 1 V A $end
$var wire 1 I B $end
$var wire 1 H C $end
$var wire 1 & Y $end
$upscope $end
$upscope $end
$upscope $end
$scope module U4 $end
$var wire 1 8 A $end
$var wire 1 , B $end
$var wire 1 - C $end
$var wire 1 W RES1 $end
$var wire 1 X RES2 $end
$var wire 1 % Y $end
$scope module U3 $end
$var wire 1 8 A $end
$var wire 1 W B $end
$var wire 1 X C $end
$var wire 1 % Y $end
$upscope $end
$upscope $end
$scope module U5 $end
$var wire 1 9 A $end
$var wire 1 : B $end
$var wire 1 . C $end
$var wire 1 ! GND $end
$var wire 1 $ Y $end
$var wire 2 Y S [1:0] $end
$scope module U5 $end
$var wire 1 Z A $end
$var wire 1 ! B $end
$var wire 1 . C $end
$var wire 1 [ D $end
$var wire 2 \ S [1:0] $end
$var wire 1 $ Y $end
$var wire 1 ] OUT2 $end
$var wire 1 ^ OUT1 $end
$scope module mux1 $end
$var wire 1 _ A $end
$var wire 1 Z B $end
$var wire 1 ! C $end
$var wire 1 ^ Y $end
$upscope $end
$scope module mux2 $end
$var wire 1 ` A $end
$var wire 1 . B $end
$var wire 1 [ C $end
$var wire 1 ] Y $end
$upscope $end
$scope module mux3 $end
$var wire 1 a A $end
$var wire 1 ^ B $end
$var wire 1 ] C $end
$var wire 1 $ Y $end
$upscope $end
$upscope $end
$upscope $end
$scope module U6 $end
$var wire 1 0 A $end
$var wire 1 1 B $end
$var wire 1 2 C $end
$var wire 1 ! GND $end
$var wire 1 " VCC $end
$var wire 1 # Y $end
$var wire 3 b S [2:0] $end
$scope module U6 $end
$var wire 1 " A $end
$var wire 1 ! B $end
$var wire 1 ! C $end
$var wire 1 ! D $end
$var wire 1 ! E $end
$var wire 1 " F $end
$var wire 1 " G $end
$var wire 1 ! H $end
$var wire 3 c S [2:0] $end
$var wire 1 # Y $end
$var wire 1 d OUT2 $end
$var wire 1 e OUT1 $end
$scope module mux1 $end
$var wire 1 " A $end
$var wire 1 ! B $end
$var wire 1 ! C $end
$var wire 1 ! D $end
$var wire 2 f S [1:0] $end
$var wire 1 e Y $end
$var wire 1 g OUT2 $end
$var wire 1 h OUT1 $end
$scope module mux1 $end
$var wire 1 i A $end
$var wire 1 " B $end
$var wire 1 ! C $end
$var wire 1 h Y $end
$upscope $end
$scope module mux2 $end
$var wire 1 j A $end
$var wire 1 ! B $end
$var wire 1 ! C $end
$var wire 1 g Y $end
$upscope $end
$scope module mux3 $end
$var wire 1 k A $end
$var wire 1 h B $end
$var wire 1 g C $end
$var wire 1 e Y $end
$upscope $end
$upscope $end
$scope module mux2 $end
$var wire 1 ! A $end
$var wire 1 " B $end
$var wire 1 " C $end
$var wire 1 ! D $end
$var wire 2 l S [1:0] $end
$var wire 1 d Y $end
$var wire 1 m OUT2 $end
$var wire 1 n OUT1 $end
$scope module mux1 $end
$var wire 1 o A $end
$var wire 1 ! B $end
$var wire 1 " C $end
$var wire 1 n Y $end
$upscope $end
$scope module mux2 $end
$var wire 1 p A $end
$var wire 1 " B $end
$var wire 1 ! C $end
$var wire 1 m Y $end
$upscope $end
$scope module mux3 $end
$var wire 1 q A $end
$var wire 1 n B $end
$var wire 1 m C $end
$var wire 1 d Y $end
$upscope $end
$upscope $end
$scope module mux3 $end
$var wire 1 r A $end
$var wire 1 e B $end
$var wire 1 d C $end
$var wire 1 # Y $end
$upscope $end
$upscope $end
$upscope $end
$upscope $end
$enddefinitions $end
#0
$dumpvars
xr
xq
xp
xo
xn
xm
bx l
xk
xj
xi
xh
0g
bx f
xe
xd
bx c
bx b
xa
x`
x_
x^
x]
bx \
x[
xZ
bx Y
xX
xW
xV
xU
xT
xS
xR
xQ
bx P
xO
xN
xM
xL
xK
bx J
xI
xH
bx G
bx F
xE
xD
xC
xB
xA
bx @
x?
x>
bx =
x<
x;
x:
x9
x8
x7
x6
x5
x4
x3
x2
x1
x0
x/
x.
x-
x,
x+
x*
x)
x(
x'
x&
x%
x$
x#
1"
0!
$end
#1
0(
1<
0;
0*
0)
0/
#2
1(
0<
1;
1*
#3
0*
1)
#4
0(
1<
0;
1*
#5
1(
0*
0)
1/
#6
0(
0<
1;
1*
#7
0*
1)
#8
1(
1<
0;
1*
#9
1A
0'
1>
1?
0B
0C
0D
0E
0+
04
b0 =
b0 @
03
#10
0A
1'
0>
0?
1B
1+
#11
1'
1>
1?
1B
1C
1D
0+
b1 =
b1 @
14
#12
0'
0B
0>
0?
1A
1+
#13
1'
1>
1?
1A
0C
0D
1E
0+
04
b10 =
b10 @
13
#14
0'
0A
0>
0?
1B
1+
#15
1>
1?
1B
1C
1D
0+
b11 =
b11 @
14
#16
0B
1'
0>
0?
1A
1+
#17
0&
0I
1H
0L
1K
1R
0Q
0M
0N
0O
0S
0T
0U
b0 J
b0 P
0V
07
06
b0 F
b0 G
05
#18
1&
1I
0H
1L
0K
0R
1Q
1M
1N
1S
1T
b1 J
b1 P
b1 F
b1 G
17
#19
1&
0L
1K
1I
1R
0Q
0H
0M
0N
1O
0S
0T
1U
b10 J
b10 P
07
b10 F
b10 G
16
#20
0&
0I
1H
1L
0K
0R
1Q
1M
1N
1S
1T
b11 J
b11 P
b11 F
b11 G
17
#21
0L
1K
0I
1R
0Q
1H
0M
0N
0O
0S
0T
0U
1&
b0 J
b0 P
1V
07
06
b100 F
b100 G
15
#22
0&
1I
0H
1L
0K
0R
1Q
1M
1N
1S
1T
b1 J
b1 P
b101 F
b101 G
17
#23
0&
0L
1K
1I
1R
0Q
0H
0M
0N
1O
0S
0T
1U
b10 J
b10 P
07
b110 F
b110 G
16
#24
1&
0I
1H
1L
0K
0R
1Q
1M
1N
1S
1T
b11 J
b11 P
b111 F
b111 G
17
#25
1%
1W
1X
0-
0,
08
#26
0%
0W
1-
#27
0-
1,
#28
0X
1-
#29
1%
1W
1X
0-
0,
18
#30
0W
1-
#31
0-
1,
#32
0%
0X
1-
#33
1$
1^
1Z
1[
0]
0_
0`
0a
0.
0:
b0 Y
b0 \
09
#34
0$
0^
0Z
0[
1]
1.
#35
1Z
1[
1]
1_
1`
0.
b1 Y
b1 \
1:
#36
0]
0Z
0[
1.
#37
1^
1Z
1[
0_
0`
1a
0.
0:
b10 Y
b10 \
19
#38
0^
1$
0Z
0[
1]
1.
#39
1$
1Z
1[
1]
1_
1`
0.
b11 Y
b11 \
1:
#40
0$
0]
0Z
0[
1.
#43
1#
1e
0d
1h
0n
1m
0i
0j
0k
0o
0p
0q
b0 f
b0 l
0r
02
01
b0 b
b0 c
00
#44
0#
0e
1d
0h
1n
0m
1i
1j
1o
1p
b1 f
b1 l
b1 b
b1 c
12
#45
1h
0n
1m
1d
0i
0j
1k
0o
0p
1q
b10 f
b10 l
02
b10 b
b10 c
11
#46
0d
0h
1n
0m
1i
1j
1o
1p
b11 f
b11 l
b11 b
b11 c
12
#47
1e
0#
1h
0n
1m
0d
0i
0j
0k
0o
0p
0q
b0 f
b0 l
1r
02
01
b100 b
b100 c
10
#48
1#
0e
1d
0h
1n
0m
1i
1j
1o
1p
b1 f
b1 l
b101 b
b101 c
12
#49
1#
1h
0n
1m
1d
0i
0j
1k
0o
0p
1q
b10 f
b10 l
02
b110 b
b110 c
11
#50
0#
0d
0h
1n
0m
1i
1j
1o
1p
b11 f
b11 l
b111 b
b111 c
12
