PROYECTO_02/CODIGO/uP.v
//PROYECTO 02
//GABRIEL FONG

module PROGRAMCOUNTER(input wire clk, reset,enable,incPC,
                input wire [11:0]LOAD,
                output reg[11:0]PC);

  always @ (posedge clk, posedge reset ) begin //REALIZAMOS UN ALWAYS PARA QUE SE EJECUTE EN TODOO MOMENTO Y CAMBIE EN EL FLANCO DE RELOJ
  if (reset)  //RESETEA EL VALOR EN 0 LOS 12 BITS
    PC <= 12'b0;
  else if (incPC) //SI EL LOAD ES 1 COLOCAR EN LA SALIDA EL VALOR PRE-COLOCADO
  PC <= LOAD;
  else if (enable) //SI ENABLE ES 1 SUMA 1 EN CADA FLANCO DE RELOJ, SI NO NO SUMA
    PC <= PC + 1;
  end
endmodule

module PROGRAMROM (input wire [11:0]PC, // DIRECCION DE 12 BITS
  output wire [7:0]PROGRAM_BYTE); //TAMAÑO DEL DATO DE 8 BITS

  reg [7:0] MEM[0:4095]; //MEM ES DE TAMAÑO DE 2^12 = 4096 Y CREA EL ARREGLO PARA NUESTROS DATOS
  initial begin         //INICIAMOS LA LECTURA DE NUESTRA LISTA
    $readmemh("memory.list", MEM);//LEEMOS LOS VALORES DE LA LISTA EN BINARIO
  end
  assign PROGRAM_BYTE = MEM[PC]; //LE ASIGANMOS EL VALOR DE MEM EN LA DIRECCION INGRESADA
endmodule // ROM

//FLIPFLOP DE 8 BITS
module FETCH (input wire clk, reset, enable,
              input wire [7:0]PROGRAM_BYTE,
              output reg [3:0]INSTR,
              output reg [3:0]OPRND);
    always @ ( posedge clk, posedge reset ) begin
      if (reset) begin
        INSTR <= 4'b0;
        OPRND <= 4'b0;
      end
      else if (enable) begin //SI EL ENABLE == 1 DEJA PASAR EL VALOR DE D A LA SALIDA Q
        INSTR[3:0]<= PROGRAM_BYTE[7:4]; //LOS 4 BITS MAS SIGNIFICATIVOS SE DIRIGEN HACIA INSTR
        OPRND[3:0]<= PROGRAM_BYTE[3:0]; //LOS 4 BITS MENOS SIGNIFICATIVOS SE DIRIGEN HACIA OPRND
      end
    end
endmodule // FETCH
module flipflopD (input wire clk, reset, enable, D,
                  output reg Q);

    always @ ( posedge clk, posedge reset ) begin
      if (reset)
        Q <= 1'b0;
      else if (enable)  //SI EL ENABLE == 1 DEJA PASAR EL VALOR DE D A LA SALIDA Q
        Q <= D;
    end
endmodule // flipflopD

module PHASE(input wire clk, reset, enable,//flipflopT
                output wire Q);

    wire D;
    not U1(D,Q); // TOMAMOS EL VALOR DE LA SALIDA Y XOR CON 1
    //SE UTILIZO LA XOR POR LA TABLA DE VERDAD, CUANDO EL DATO DE LA ENTRADA ES EL MISMO = 0, DIFERENTES = 1
    flipflopD U1(clk, reset, enable, D, Q);

endmodule
module BUSDRIVER (input wire [3:0]D,
                input wire enable,
                output wire [3:0]Y);
  assign Y = enable ? D : 4'bz;
 //si enable = 1 deja pasar el dato de D, sino en alta impedancia

endmodule // BUSDRIVER

module DECODE(input wire[6:0]IN,
              output reg [12:0]OUTS);//LA SALIDA SON TODAS LAS SENALES

    always @ ( IN ) begin
      casex(IN)
        7'bxxxxxx0: OUTS <= 13'b1000000001000;//any
        7'b00001x1: OUTS <= 13'b0100000001000;//JC
        7'b00000x1: OUTS <= 13'b1000000001000;// JC
        7'b00011x1: OUTS <= 13'b1000000001000;// JNC
        7'b00010x1: OUTS <= 13'b0100000001000;// JNC
        7'b0010xx1: OUTS <= 13'b0001001000010;// CMPI
        7'b0011xx1: OUTS <= 13'b1001001100000;// CMPM
        7'b0100xx1: OUTS <= 13'b0011010000010;// LIT
        7'b0101xx1: OUTS <= 13'b0011010000100;// IN
        7'b0110xx1: OUTS <= 13'b1011010100000;// LD
        7'b0111xx1: OUTS <= 13'b1000000111000;// ST
        7'b1000x11: OUTS <= 13'b0100000001000;// JZ
        7'b1000x01: OUTS <= 13'b1000000001000;// JZ
        7'b1001x11: OUTS <= 13'b1000000001000;// JNZ
        7'b1001x01: OUTS <= 13'b0100000001000;// JNZ
        7'b1010xx1: OUTS <= 13'b0011011000010;// ADDI
        7'b1011xx1: OUTS <= 13'b1011011100000;// ADDM
        7'b1100xx1: OUTS <= 13'b0100000001000;// JMP
        7'b1101xx1: OUTS <= 13'b0000000001001;// OUT
        7'b1110xx1: OUTS <= 13'b0011100000010;// NANDI
        7'b1111xx1: OUTS <= 13'b1011100100000;// NANDM
        default: OUTS <= 13'b1111111111111;

      endcase

    end
    //assign OUTSIG = OUTS;
endmodule

module ACCUMULATOR(input wire clk, reset, enable,
              input wire [3:0]ALUS,
              output reg [3:0]ACCU);
    always @ ( posedge clk, posedge reset ) begin
      if (reset) begin
        ACCU<= 4'b0;
      end
      else if (enable) begin //SI EL ENABLE == 1 DEJA PASAR EL VALOR DE D A LA SALIDA Q
        ACCU<= ALUS; //LOS 4 BITS DE LA SALIDA DE LA ALU SE DIRIGEN HACIA EL ACUMULADOR
      end
    end
endmodule

module ALU (input wire [3:0]ACCU,DATA_BUS, //ACCU = A  VIENE DEL ACUMULADOR  DATA_BUS = B VIENE DEL BUFFER DATA_BUS
            input wire [2:0]F,      //SELECTOR DE LAS OPERACIONES
            output wire [3:0]ALU_OUT,
            output wire CARRY,ZERO); //SALIDA

  reg  [4:0]OUT5;
  always @ (ACCU,DATA_BUS,F ) begin
    case (F)
      3'b000: OUT5 <= ACCU;
      3'b001: OUT5 <= ACCU - DATA_BUS;
      3'b010: OUT5 <= DATA_BUS;
      3'b011: OUT5 <= ACCU + DATA_BUS;
      3'b100: OUT5 <= {1'b0, (ACCU ~& DATA_BUS)};
      default: OUT5 <= 5'b00000;
    endcase
  end
  assign ALU_OUT = OUT5[3:0];
  assign CARRY = OUT5[4];
  assign ZERO = ~(ALU_OUT[3]| ALU_OUT[2]| ALU_OUT[1]|ALU_OUT[0]);
  //assign ZERO = (OUT5 == 4'b0000) ? 1:0;

endmodule // ALU

module FLAGS (input wire clk, reset,enable,
              input wire [1:0]flags,
              output reg [1:0]out_flags);
    always @ ( posedge clk, posedge reset ) begin
      if (reset)
        out_flags<= 2'b0;

    else if (enable)  //SI EL ENABLE == 1 DEJA PASAR EL VALOR DE D A LA SALIDA Q
          out_flags <= flags;
        //out_flags[1]<= flags[1]; //Carry
        //out_flags[0]<= flags[0];//zero
    end
endmodule // FLAGS

module RAM(input wire csRAM,weRAM,
          input wire [11:0]address_RAM,
          inout wire [3:0]data_bus);
  reg[3:0] dataout;
  reg[3:0] MEM[0:4095];
  //ST
  always @ ( address_RAM or data_bus or weRAM ) begin
    if (csRAM && weRAM) begin
      MEM[address_RAM]<=data_bus;
    end
  end
  //LOAD
  always @ (address_RAM or csRAM) begin
    if (csRAM && !weRAM)begin
      dataout<= MEM[address_RAM];
    end
  end

  assign data_bus = (csRAM &! weRAM) ? dataout : 4'bz;

endmodule

module uP(input wire clock,reset,
          input wire [3:0]pushbuttons,
          output wire phase, c_flag, z_flag,
          output wire [3:0]instr, oprnd,accu, data_bus, FF_out,
          output wire [7:0]program_byte,
          output wire [11:0]PC,address_RAM);

  wire incPC, loadPC, loadA,loadFlags,csRAM, weRAM, oeALU, oeIN, oeOprnd, loadOut,flag_c,flag_z;
  wire enphase = 1;
  wire [2:0]S_A;//selector de la ALU
  wire [3:0]ALU_O;//salida de la ALU
  assign address_RAM = {oprnd,program_byte};
  assign nphase = ~phase;
  PROGRAMCOUNTER PROGCOUNT(clock,reset,incPC,loadPC,address_RAM,PC);
  PROGRAMROM ROM(PC,program_byte);
  FETCH Fetch(clock,reset,nphase,program_byte,instr,oprnd);
  BUSDRIVER B1(oprnd,oeOprnd,data_bus);
  PHASE Phase(clock,reset,enphase,phase);
  DECODE Deco({instr,c_flag,z_flag,phase},{incPC,loadPC,loadA,loadFlags,S_A,csRAM,weRAM,oeALU,oeIN,oeOprnd,loadOut});
  ACCUMULATOR Accu(clock, reset, loadA,ALU_O,accu);
  ALU alu(accu,data_bus,S_A,ALU_O,flag_c,flag_z);
  BUSDRIVER B2(ALU_O, oeALU,data_bus);
  FLAGS flag(clock, reset, loadFlags,{flag_c,flag_z},{c_flag,z_flag});
  BUSDRIVER Inputs(pushbuttons,oeIN,data_bus);
  ACCUMULATOR OUTPUTS(clock,reset,loadOut,data_bus,FF_out);
  RAM ram(csRAM,weRAM,address_RAM,data_bus);

endmodule

PROYECTO_02/CODIGO/uP_tb.v
//PROYECTO 02
//GABRIEL FONG
//Testebench

module testbench ();
    reg clock, reset;
    reg [3:0] pushbuttons;
    wire phase, c_flag, z_flag;
    wire [3:0] instr, oprnd, accu, data_bus, FF_out;
    wire [7:0] program_byte;
    wire [11:0] PC, address_RAM;

    uP uPmodule(.clock(clock),
                .reset(reset),
                .pushbuttons(pushbuttons),
                .phase(phase),
                .c_flag(c_flag),
                .z_flag(z_flag),
                .instr(instr),
                .oprnd(oprnd),
                .accu(accu),
                .data_bus(data_bus),
                .FF_out(FF_out),
                .program_byte(program_byte),
                .PC(PC),
                .address_RAM(address_RAM));

    initial
      #1000 $finish;

    always
        #5 clock = ~clock;

    initial begin
        clock = 0; reset = 0; pushbuttons = 4'b0110;
        #2 reset = 1;
        #1 reset = 0;
        $display("\n");
        $display("Bienvenido al testbench del NIBBLER");
        $display("\n");

      end

    initial begin
        $dumpfile("uP_tb.vcd");
        $dumpvars(0, testbench);
    end

    initial begin
    #5 pushbuttons = 4'b1100;
    #160 pushbuttons = 4'b0011;
    #320 pushbuttons = 4'b0010;

    end
endmodule // testbench

PROYECTO_02/CODIGO/uP_tb.vcd
$date
	Sat Nov 21 15:42:39 2020
$end
$version
	Icarus Verilog
$end
$timescale
	1ps
$end
$scope module testbench $end
$var wire 4 ! data_bus [3:0] $end
$var wire 1 " z_flag $end
$var wire 8 # program_byte [7:0] $end
$var wire 1 $ phase $end
$var wire 4 % oprnd [3:0] $end
$var wire 4 & instr [3:0] $end
$var wire 1 ' c_flag $end
$var wire 12 ( address_RAM [11:0] $end
$var wire 4 ) accu [3:0] $end
$var wire 12 * PC [11:0] $end
$var wire 4 + FF_out [3:0] $end
$var reg 1 , clock $end
$var reg 4 - pushbuttons [3:0] $end
$var reg 1 . reset $end
$scope module uPmodule $end
$var wire 1 , clock $end
$var wire 4 / data_bus [3:0] $end
$var wire 1 0 enphase $end
$var wire 1 1 nphase $end
$var wire 4 2 pushbuttons [3:0] $end
$var wire 1 . reset $end
$var wire 1 " z_flag $end
$var wire 1 3 weRAM $end
$var wire 8 4 program_byte [7:0] $end
$var wire 1 $ phase $end
$var wire 4 5 oprnd [3:0] $end
$var wire 1 6 oeOprnd $end
$var wire 1 7 oeIN $end
$var wire 1 8 oeALU $end
$var wire 1 9 loadPC $end
$var wire 1 : loadOut $end
$var wire 1 ; loadFlags $end
$var wire 1 < loadA $end
$var wire 4 = instr [3:0] $end
$var wire 1 > incPC $end
$var wire 1 ? flag_z $end
$var wire 1 @ flag_c $end
$var wire 1 A csRAM $end
$var wire 1 ' c_flag $end
$var wire 12 B address_RAM [11:0] $end
$var wire 4 C accu [3:0] $end
$var wire 3 D S_A [2:0] $end
$var wire 12 E PC [11:0] $end
$var wire 4 F FF_out [3:0] $end
$var wire 4 G ALU_O [3:0] $end
$scope module Accu $end
$var wire 1 , clk $end
$var wire 1 < enable $end
$var wire 1 . reset $end
$var wire 4 H ALUS [3:0] $end
$var reg 4 I ACCU [3:0] $end
$upscope $end
$scope module B1 $end
$var wire 4 J Y [3:0] $end
$var wire 1 6 enable $end
$var wire 4 K D [3:0] $end
$upscope $end
$scope module B2 $end
$var wire 4 L Y [3:0] $end
$var wire 1 8 enable $end
$var wire 4 M D [3:0] $end
$upscope $end
$scope module Deco $end
$var wire 7 N IN [6:0] $end
$var reg 13 O OUTS [12:0] $end
$upscope $end
$scope module Fetch $end
$var wire 1 , clk $end
$var wire 1 1 enable $end
$var wire 1 . reset $end
$var wire 8 P PROGRAM_BYTE [7:0] $end
$var reg 4 Q INSTR [3:0] $end
$var reg 4 R OPRND [3:0] $end
$upscope $end
$scope module Inputs $end
$var wire 4 S D [3:0] $end
$var wire 4 T Y [3:0] $end
$var wire 1 7 enable $end
$upscope $end
$scope module OUTPUTS $end
$var wire 4 U ALUS [3:0] $end
$var wire 1 , clk $end
$var wire 1 : enable $end
$var wire 1 . reset $end
$var reg 4 V ACCU [3:0] $end
$upscope $end
$scope module PROGCOUNT $end
$var wire 12 W LOAD [11:0] $end
$var wire 1 , clk $end
$var wire 1 > enable $end
$var wire 1 9 incPC $end
$var wire 1 . reset $end
$var reg 12 X PC [11:0] $end
$upscope $end
$scope module Phase $end
$var wire 1 Y D $end
$var wire 1 , clk $end
$var wire 1 0 enable $end
$var wire 1 . reset $end
$var wire 1 $ Q $end
$scope module U1 $end
$var wire 1 Y D $end
$var wire 1 , clk $end
$var wire 1 0 enable $end
$var wire 1 . reset $end
$var reg 1 $ Q $end
$upscope $end
$upscope $end
$scope module ROM $end
$var wire 12 Z PC [11:0] $end
$var wire 8 [ PROGRAM_BYTE [7:0] $end
$upscope $end
$scope module alu $end
$var wire 4 \ ACCU [3:0] $end
$var wire 4 ] DATA_BUS [3:0] $end
$var wire 3 ^ F [2:0] $end
$var wire 1 ? ZERO $end
$var wire 1 @ CARRY $end
$var wire 4 _ ALU_OUT [3:0] $end
$var reg 5 ` OUT5 [4:0] $end
$upscope $end
$scope module flag $end
$var wire 1 , clk $end
$var wire 1 ; enable $end
$var wire 2 a flags [1:0] $end
$var wire 1 . reset $end
$var reg 2 b out_flags [1:0] $end
$upscope $end
$scope module ram $end
$var wire 12 c address_RAM [11:0] $end
$var wire 1 A csRAM $end
$var wire 4 d data_bus [3:0] $end
$var wire 1 3 weRAM $end
$var reg 4 e dataout [3:0] $end
$upscope $end
$upscope $end
$upscope $end
$enddefinitions $end
#0
$dumpvars
bx e
bx d
bx c
bx b
bx a
bx `
bx _
bx ^
bx ]
bx \
bx [
bx Z
xY
bx X
bx W
bx V
bx U
bx T
b110 S
bx R
bx Q
bx P
bx O
bx N
bx M
bx L
bx K
bx J
bx I
bx H
bx G
bx F
bx E
bx D
bx C
bx B
xA
x@
x?
x>
bx =
x<
x;
x:
x9
x8
x7
x6
bx 5
bx 4
x3
b110 2
x1
10
bx /
0.
b110 -
0,
bx +
bx *
bx )
bx (
x'
bx &
bx %
x$
bx #
x"
bx !
$end
#2
1?
b0 !
b0 /
b0 J
b0 L
b0 T
b0 U
b0 ]
b0 d
0:
06
07
18
03
0A
b0 D
b0 ^
0;
0<
09
1>
b0 G
b0 H
b0 M
b0 _
b1 a
0@
b1000000001000 O
b0 `
1Y
11
0"
0'
b1000111 #
b1000111 4
b1000111 P
b1000111 [
b0 *
b0 E
b0 X
b0 Z
b1000111 (
b1000111 B
b1000111 W
b1000111 c
b0 %
b0 5
b0 K
b0 R
b0 &
b0 =
b0 Q
b0 N
0$
b0 )
b0 C
b0 I
b0 \
b0 b
b0 +
b0 F
b0 V
1.
#3
0.
#5
b0 a
0?
b111 G
b111 H
b111 M
b111 _
b111 `
b111 !
b111 /
b111 J
b111 L
b111 T
b111 U
b111 ]
b111 d
16
08
b10 D
b10 ^
1;
1<
0>
b11010000010 O
0Y
01
1$
b111 %
b111 5
b111 K
b111 R
b100001 N
b100 &
b100 =
b100 Q
b11101011100 (
b11101011100 B
b11101011100 W
b11101011100 c
b1011100 #
b1011100 4
b1011100 P
b1011100 [
b1 *
b1 E
b1 X
b1 Z
b1100 -
b1100 2
b1100 S
1,
#10
0,
#15
06
18
b0 D
b0 ^
0;
0<
1>
b1000000001000 O
1Y
11
b100000 N
0$
b111 )
b111 C
b111 I
b111 \
1,
#20
0,
#25
b1100 G
b1100 H
b1100 M
b1100 _
b1100 `
b1100 !
b1100 /
b1100 J
b1100 L
b1100 T
b1100 U
b1100 ]
b1100 d
17
08
b10 D
b10 ^
1;
1<
0>
b11010000100 O
0Y
01
1$
b1100 %
b1100 5
b1100 K
b1100 R
b101001 N
b101 &
b101 =
b101 Q
b110010100011 (
b110010100011 B
b110010100011 W
b110010100011 c
b10100011 #
b10100011 4
b10100011 P
b10100011 [
b10 *
b10 E
b10 X
b10 Z
1,
#30
0,
#35
07
18
b0 D
b0 ^
0;
0<
1>
b1000000001000 O
1Y
11
b101000 N
0$
b1100 )
b1100 C
b1100 I
b1100 \
1,
#40
0,
#45
b1111 G
b1111 H
b1111 M
b1111 _
b1111 `
b11 !
b11 /
b11 J
b11 L
b11 T
b11 U
b11 ]
b11 d
16
08
b11 D
b11 ^
1;
1<
0>
b11011000010 O
0Y
01
1$
b11 %
b11 5
b11 K
b11 R
b1010001 N
b1010 &
b1010 =
b1010 Q
b1111101010 (
b1111101010 B
b1111101010 W
b1111101010 c
b11101010 #
b11101010 4
b11101010 P
b11101010 [
b11 *
b11 E
b11 X
b11 Z
1,
#50
0,
#55
b1111 !
b1111 /
b1111 J
b1111 L
b1111 T
b1111 U
b1111 ]
b1111 d
06
18
b0 D
b0 ^
0;
0<
1>
b1111 G
b1111 H
b1111 M
b1111 _
b0 a
0@
b1000000001000 O
b1111 `
1Y
11
b1010000 N
0$
b1111 )
b1111 C
b1111 I
b1111 \
1,
#60
0,
#65
b101 G
b101 H
b101 M
b101 _
b101 `
b1010 !
b1010 /
b1010 J
b1010 L
b1010 T
b1010 U
b1010 ]
b1010 d
16
08
b100 D
b100 ^
1;
1<
0>
b11100000010 O
0Y
01
1$
b1010 %
b1010 5
b1010 K
b1010 R
b1110001 N
b1110 &
b1110 =
b1110 Q
b101000101101 (
b101000101101 B
b101000101101 W
b101000101101 c
b101101 #
b101101 4
b101101 P
b101101 [
b100 *
b100 E
b100 X
b100 Z
1,
#70
0,
#75
b101 !
b101 /
b101 J
b101 L
b101 T
b101 U
b101 ]
b101 d
06
18
b0 D
b0 ^
0;
0<
1>
b101 G
b101 H
b101 M
b101 _
b1000000001000 O
b101 `
1Y
11
b1110000 N
0$
b101 )
b101 C
b101 I
b101 \
1,
#80
0,
#85
b10 a
1@
b1000 G
b1000 H
b1000 M
b1000 _
b11000 `
b1101 !
b1101 /
b1101 J
b1101 L
b1101 T
b1101 U
b1101 ]
b1101 d
16
08
b1 D
b1 ^
1;
0>
b1001000010 O
0Y
01
1$
b1101 %
b1101 5
b1101 K
b1101 R
b10001 N
b10 &
b10 =
b10 Q
b110101110000 (
b110101110000 B
b110101110000 W
b110101110000 c
b1110000 #
b1110000 4
b1110000 P
b1110000 [
b101 *
b101 E
b101 X
b101 Z
1,
#90
0,
#95
b101 G
b101 H
b101 M
b101 _
b0 a
0@
b101 `
b101 !
b101 /
b101 J
b101 L
b101 T
b101 U
b101 ]
b101 d
06
18
b0 D
b0 ^
0;
1>
b1000000001000 O
1Y
11
1'
b10100 N
0$
b10 b
1,
#100
0,
#105
13
1A
b1000000111000 O
0Y
01
1$
b0 %
b0 5
b0 K
b0 R
b111101 N
b111 &
b111 =
b111 Q
b10000 (
b10000 B
b10000 W
b10000 c
b10000 #
b10000 4
b10000 P
b10000 [
b110 *
b110 E
b110 X
b110 Z
1,
#110
0,
#115
03
0A
b1000000001000 O
1Y
11
b1001011 (
b1001011 B
b1001011 W
b1001011 c
b1001011 #
b1001011 4
b1001011 P
b1001011 [
b111 *
b111 E
b111 X
b111 Z
b111100 N
0$
1,
#120
0,
#125
b1011 G
b1011 H
b1011 M
b1011 _
b1011 `
b1011 !
b1011 /
b1011 J
b1011 L
b1011 T
b1011 U
b1011 ]
b1011 d
16
08
b10 D
b10 ^
1;
1<
0>
b11010000010 O
0Y
01
1$
b1011 %
b1011 5
b1011 K
b1011 R
b100101 N
b100 &
b100 =
b100 Q
b101101110001 (
b101101110001 B
b101101110001 W
b101101110001 c
b1110001 #
b1110001 4
b1110001 P
b1110001 [
b1000 *
b1000 E
b1000 X
b1000 Z
1,
#130
0,
#135
06
18
b0 D
b0 ^
0;
0<
1>
b1000000001000 O
1Y
11
0'
b100000 N
0$
b1011 )
b1011 C
b1011 I
b1011 \
b0 b
1,
#140
0,
#145
13
1A
b1000000111000 O
0Y
01
1$
b1 %
b1 5
b1 K
b1 R
b111001 N
b111 &
b111 =
b111 Q
b100000000 (
b100000000 B
b100000000 W
b100000000 c
b0 #
b0 4
b0 P
b0 [
b1001 *
b1001 E
b1001 X
b1001 Z
1,
#150
0,
#155
03
0A
b1000000001000 O
1Y
11
b110110000 (
b110110000 B
b110110000 W
b110110000 c
b10110000 #
b10110000 4
b10110000 P
b10110000 [
b1010 *
b1010 E
b1010 X
b1010 Z
b111000 N
0$
1,
#160
0,
#165
1?
b0 G
b0 H
b0 M
b0 _
b11 a
1@
b101 e
b10000 `
b101 !
b101 /
b101 J
b101 L
b101 T
b101 U
b101 ]
b101 d
08
1A
b11 D
b11 ^
1;
1<
b1011011100000 O
0Y
01
1$
b0 %
b0 5
b0 K
b0 R
b1011001 N
b1011 &
b1011 =
b1011 Q
b10000 (
b10000 B
b10000 W
b10000 c
b10000 #
b10000 4
b10000 P
b10000 [
b1011 *
b1011 E
b1011 X
b1011 Z
1,
b11 -
b11 2
b11 S
#170
0,
#175
1?
b0 !
b0 /
b0 J
b0 L
b0 T
b0 U
b0 ]
b0 d
18
0A
b0 D
b0 ^
0;
0<
b0 G
b0 H
b0 M
b0 _
b1 a
0@
bx e
b1000000001000 O
b0 `
1Y
11
1"
1'
b1010011 (
b1010011 B
b1010011 W
b1010011 c
b1010011 #
b1010011 4
b1010011 P
b1010011 [
b1100 *
b1100 E
b1100 X
b1100 Z
b1011110 N
0$
b0 )
b0 C
b0 I
b0 \
b11 b
1,
#180
0,
#185
b0 a
0?
b11 G
b11 H
b11 M
b11 _
b11 `
b11 !
b11 /
b11 J
b11 L
b11 T
b11 U
b11 ]
b11 d
17
08
b10 D
b10 ^
1;
1<
0>
b11010000100 O
0Y
01
1$
b11 %
b11 5
b11 K
b11 R
b101111 N
b101 &
b101 =
b101 Q
b1101100001 (
b1101100001 B
b1101100001 W
b1101100001 c
b1100001 #
b1100001 4
b1100001 P
b1100001 [
b1101 *
b1101 E
b1101 X
b1101 Z
1,
#190
0,
#195
07
18
b0 D
b0 ^
0;
0<
1>
b1000000001000 O
1Y
11
0"
0'
b101000 N
0$
b11 )
b11 C
b11 I
b11 \
b0 b
1,
#200
0,
#205
b0 a
0?
b1011 G
b1011 H
b1011 M
b1011 _
b1011 `
b1011 e
b1011 !
b1011 /
b1011 J
b1011 L
b1011 T
b1011 U
b1011 ]
b1011 d
08
1A
b10 D
b10 ^
1;
1<
b1011010100000 O
0Y
01
1$
b1 %
b1 5
b1 K
b1 R
b110001 N
b110 &
b110 =
b110 Q
b100000000 (
b100000000 B
b100000000 W
b100000000 c
b0 #
b0 4
b0 P
b0 [
b1110 *
b1110 E
b1110 X
b1110 Z
1,
#210
0,
#215
b1011 !
b1011 /
b1011 J
b1011 L
b1011 T
b1011 U
b1011 ]
b1011 d
18
0A
b0 D
b0 ^
0;
0<
bx e
b1000000001000 O
1Y
11
b111011011 (
b111011011 B
b111011011 W
b111011011 c
b11011011 #
b11011011 4
b11011011 P
b11011011 [
b1111 *
b1111 E
b1111 X
b1111 Z
b110000 N
0$
b1011 )
b1011 C
b1011 I
b1011 \
1,
#220
0,
#225
1:
0>
b1001 O
0Y
01
1$
b1011 %
b1011 5
b1011 K
b1011 R
b1101001 N
b1101 &
b1101 =
b1101 Q
b101111001001 (
b101111001001 B
b101111001001 W
b101111001001 c
b11001001 #
b11001001 4
b11001001 P
b11001001 [
b10000 *
b10000 E
b10000 X
b10000 Z
1,
#230
0,
#235
0:
1>
b1000000001000 O
1Y
11
b1101000 N
0$
b1011 +
b1011 F
b1011 V
1,
#240
0,
#245
19
0>
b100000001000 O
0Y
01
1$
b1001 %
b1001 5
b1001 K
b1001 R
b1100001 N
b1100 &
b1100 =
b1100 Q
b100100010000 (
b100100010000 B
b100100010000 W
b100100010000 c
b10000 #
b10000 4
b10000 P
b10000 [
b10001 *
b10001 E
b10001 X
b10001 Z
1,
#250
0,
#255
09
1>
b1000000001000 O
1Y
11
b100101000101 (
b100101000101 B
b100101000101 W
b100101000101 c
b1000101 #
b1000101 4
b1000101 P
b1000101 [
b100100010000 *
b100100010000 E
b100100010000 X
b100100010000 Z
b1100000 N
0$
1,
#260
0,
#265
b101 G
b101 H
b101 M
b101 _
b101 `
b101 !
b101 /
b101 J
b101 L
b101 T
b101 U
b101 ]
b101 d
16
08
b10 D
b10 ^
1;
1<
0>
b11010000010 O
0Y
01
1$
b101 %
b101 5
b101 K
b101 R
b100001 N
b100 &
b100 =
b100 Q
b10110101100 (
b10110101100 B
b10110101100 W
b10110101100 c
b10101100 #
b10101100 4
b10101100 P
b10101100 [
b100100010001 *
b100100010001 E
b100100010001 X
b100100010001 Z
1,
#270
0,
#275
06
18
b0 D
b0 ^
0;
0<
1>
b1000000001000 O
1Y
11
b100000 N
0$
b101 )
b101 C
b101 I
b101 \
1,
#280
0,
#285
b10 a
1@
b1 G
b1 H
b1 M
b1 _
b10001 `
b1100 !
b1100 /
b1100 J
b1100 L
b1100 T
b1100 U
b1100 ]
b1100 d
16
08
b11 D
b11 ^
1;
1<
0>
b11011000010 O
0Y
01
1$
b1100 %
b1100 5
b1100 K
b1100 R
b1010001 N
b1010 &
b1010 =
b1010 Q
b110000001010 (
b110000001010 B
b110000001010 W
b110000001010 c
b1010 #
b1010 4
b1010 P
b1010 [
b100100010010 *
b100100010010 E
b100100010010 X
b100100010010 Z
1,
#290
0,
#295
b1 !
b1 /
b1 J
b1 L
b1 T
b1 U
b1 ]
b1 d
06
18
b0 D
b0 ^
0;
0<
1>
b1 G
b1 H
b1 M
b1 _
b0 a
0@
b1000000001000 O
b1 `
1Y
11
1'
b1010100 N
0$
b1 )
b1 C
b1 I
b1 \
b10 b
1,
#300
0,
#305
19
0>
b100000001000 O
0Y
01
1$
b1010 %
b1010 5
b1010 K
b1010 R
b101 N
b0 &
b0 =
b0 Q
b101001010000 (
b101001010000 B
b101001010000 W
b101001010000 c
b1010000 #
b1010000 4
b1010000 P
b1010000 [
b100100010011 *
b100100010011 E
b100100010011 X
b100100010011 Z
1,
#310
0,
#315
09
1>
b1000000001000 O
1Y
11
b101001001111 (
b101001001111 B
b101001001111 W
b101001001111 c
b1001111 #
b1001111 4
b1001111 P
b1001111 [
b101001010000 *
b101001010000 E
b101001010000 X
b101001010000 Z
b100 N
0$
1,
#320
0,
#325
b1111 G
b1111 H
b1111 M
b1111 _
b1111 `
b1111 !
b1111 /
b1111 J
b1111 L
b1111 T
b1111 U
b1111 ]
b1111 d
16
08
b10 D
b10 ^
1;
1<
0>
b11010000010 O
0Y
01
1$
b1111 %
b1111 5
b1111 K
b1111 R
b100101 N
b100 &
b100 =
b100 Q
b111111101111 (
b111111101111 B
b111111101111 W
b111111101111 c
b11101111 #
b11101111 4
b11101111 P
b11101111 [
b101001010001 *
b101001010001 E
b101001010001 X
b101001010001 Z
1,
#330
0,
#335
06
18
b0 D
b0 ^
0;
0<
1>
b1000000001000 O
1Y
11
0'
b100000 N
0$
b1111 )
b1111 C
b1111 I
b1111 \
b0 b
1,
#340
0,
#345
b1 a
1?
b0 G
b0 H
b0 M
b0 _
b0 `
b1111 !
b1111 /
b1111 J
b1111 L
b1111 T
b1111 U
b1111 ]
b1111 d
16
08
b100 D
b100 ^
1;
1<
0>
b11100000010 O
0Y
01
1$
b1110001 N
b1110 &
b1110 =
b1110 Q
b111110001011 (
b111110001011 B
b111110001011 W
b111110001011 c
b10001011 #
b10001011 4
b10001011 P
b10001011 [
b101001010010 *
b101001010010 E
b101001010010 X
b101001010010 Z
1,
#350
0,
#355
b0 !
b0 /
b0 J
b0 L
b0 T
b0 U
b0 ]
b0 d
b1 a
1?
06
18
b0 D
b0 ^
0;
0<
1>
b0 G
b0 H
b0 M
b0 _
b1000000001000 O
b0 `
1Y
11
1"
b1110010 N
0$
b0 )
b0 C
b0 I
b0 \
b1 b
1,
#360
0,
#365
19
0>
b100000001000 O
0Y
01
1$
b1011 %
b1011 5
b1011 K
b1011 R
b1000011 N
b1000 &
b1000 =
b1000 Q
b101101010000 (
b101101010000 B
b101101010000 W
b101101010000 c
b1010000 #
b1010000 4
b1010000 P
b1010000 [
b101001010011 *
b101001010011 E
b101001010011 X
b101001010011 Z
1,
#370
0,
#375
09
1>
b1000000001000 O
1Y
11
b101101001001 (
b101101001001 B
b101101001001 W
b101101001001 c
b1001001 #
b1001001 4
b1001001 P
b1001001 [
b101101010000 *
b101101010000 E
b101101010000 X
b101101010000 Z
b1000010 N
0$
1,
#380
0,
#385
b0 a
0?
b1001 G
b1001 H
b1001 M
b1001 _
b1001 `
b1001 !
b1001 /
b1001 J
b1001 L
b1001 T
b1001 U
b1001 ]
b1001 d
16
08
b10 D
b10 ^
1;
1<
0>
b11010000010 O
0Y
01
1$
b1001 %
b1001 5
b1001 K
b1001 R
b100011 N
b100 &
b100 =
b100 Q
b100100011011 (
b100100011011 B
b100100011011 W
b100100011011 c
b11011 #
b11011 4
b11011 P
b11011 [
b101101010001 *
b101101010001 E
b101101010001 X
b101101010001 Z
1,
#390
0,
#395
06
18
b0 D
b0 ^
0;
0<
1>
b1000000001000 O
1Y
11
0"
b100000 N
0$
b1001 )
b1001 C
b1001 I
b1001 \
b0 b
1,
#400
0,
#405
19
0>
b100000001000 O
0Y
01
1$
b1011 %
b1011 5
b1011 K
b1011 R
b1001 N
b1 &
b1 =
b1 Q
b101101100000 (
b101101100000 B
b101101100000 W
b101101100000 c
b1100000 #
b1100000 4
b1100000 P
b1100000 [
b101101010010 *
b101101010010 E
b101101010010 X
b101101010010 Z
1,
#410
0,
