LABORATORIO-9/CODIGO3/LAB_3.V
//LABORATORIO 9
//ELECTRONICA DIGITAL I
//GABRIEL ALEXANDER FONG PENAGOS 19722
//EJERCICIO 3

module flipflopD (input wire clk, reset, enable, D,
                  output reg Q);

    always @ ( posedge clk, posedge reset ) begin
      if (reset) begin
        Q <= 1'b0;
      end
      else if (enable) begin //SI EL ENABLE == 1 DEJA PASAR EL VALOR DE D A LA SALIDA Q
        Q <= D;
      end
    end
endmodule // flipflopD

module flipflopJK (input wire clk, reset, enable, J, K,
                  output wire Q);
   wire Qn,Kn,w1,w2, w3;
   not U1(Qn, Q);
   not U2(Kn, K);
   nand U3(w1,Kn, Q);
   nand U4(w2,J, Qn);
   nand U5(w3, w1, w2);

   flipflopD U6(clk,reset,enable,w3,Q);
   endmodule//flipflopJK

LABORATORIO-9/CODIGO3/LAB_3_tb.v
//LABORATORIO 9
//ELECTRONICA DIGITAL I
//GABRIEL ALEXANDER FONG PENAGOS 19722
//EJERCICIO 3
//TESTBENCH
module testbench ();
//Variables para el flipflopJK
reg clk, reset, enable, J, K;
wire Q;

flipflopJK U1(clk, reset, enable, J, K, Q);
always begin //REALIZAMOS EL RELOJ Y QUE CAMBIE CADA UNIDAD DE TIEMPO
  clk <= 1; #1 clk <= ~clk; #1;
end

initial begin
reset = 1;enable= 1;  //RESETEAMOS ENCENDEMOS EL ENABLE Y D = 0
#1
$display("\n");
$display(" FLIP FLOP JK ");
$display("C \t R \t E \t J \t K \t | Q");
$monitor("%b \t %b\t %b \t %b \t %b \t | %b ", clk, reset, enable,J,K, Q );
#2 reset = 0;J = 0; K = 0; //
#2 J = 0; K = 1;
#2 J = 1; K = 0;
#2 J = 1; K = 1;
#4 reset = 1;
#2 reset = 0; J = 1; K = 0;
#2 enable = 0;
#4 $finish;
end

initial begin                                                                 //INICIAMOS PARA COLOCAR LOS DATOS EN GTK WAVE
      $dumpfile("LAB_3_tb.vcd");
      $dumpvars(0, testbench);
    end

endmodule // testbench

LABORATORIO-9/CODIGO3/LAB9_3_tb.vcd
$date
	Fri Oct 30 19:55:47 2020
$end
$version
	Icarus Verilog
$end
$timescale
	1ps
$end
$scope module testbench $end
$var wire 1 ! Q $end
$var reg 1 " J $end
$var reg 1 # K $end
$var reg 1 $ clk $end
$var reg 1 % enable $end
$var reg 1 & reset $end
$scope module U1 $end
$var wire 1 " J $end
$var wire 1 # K $end
$var wire 1 ' Kn $end
$var wire 1 ( Qn $end
$var wire 1 $ clk $end
$var wire 1 % enable $end
$var wire 1 & reset $end
$var wire 1 ) w1 $end
$var wire 1 * w2 $end
$var wire 1 + w3 $end
$var wire 1 ! Q $end
$scope module U6 $end
$var wire 1 + D $end
$var wire 1 $ clk $end
$var wire 1 % enable $end
$var wire 1 & reset $end
$var reg 1 ! Q $end
$upscope $end
$upscope $end
$upscope $end
$enddefinitions $end
#0
$dumpvars
x+
x*
1)
1(
x'
1&
1%
1$
x#
x"
0!
$end
#1
0$
#2
1$
#3
0$
0+
1'
1*
0#
0"
0&
#4
1$
#5
0$
0'
1#
#6
1$
#7
0$
1+
1'
0*
0#
1"
#8
1*
0)
0(
1!
1$
#9
0$
0+
1)
0'
1#
#10
1+
0*
1(
0!
1$
#11
0$
#12
0+
1*
0(
1!
1$
#13
1+
0*
1(
0!
0$
1&
#14
1$
#15
0$
1'
0#
0&
#16
1*
0)
0(
1!
1$
#17
0$
0%
