LABORATORIO-4/Alarma_carro/ALARMACARRO.v
//ALARMA CARRO
//GABRIEL ALEXANDER FONG PENAGOS
//CARNE 19722

  module alarma_sopg(input wire A, B, C, output wire Y1);                         //Creamos el modulo de Alarma con configuracion SOP y gate leveling

    wire notA, notB, notC, w1, w2 ,w3;                                          //Creamos nuestros cables
//Compuertas NOT
    not (notA, A);
    not (notB, B);
    not (notC, C);
//operaciones
    and (w1, A, notB, notC);
    and (w2, A, notB, C);
    and (w3, A, B, C);
    or  (Y1, w1, w2, w3);

  endmodule                                                                   //Terminamos el modulo alarma_sop

  module alarma_sopo(input wire A, B, C, output wire Y2);

      assign Y2 = (A & ~B & ~C) | (A & ~B & C) | (A & B & C);
  endmodule

  module alarma_poso(input wire A, B, C, output wire Y3);

    assign Y3 = (A|B|C) & (A|B|~C) & (A|~B|C) & (A|~B|~C) & (~A|~B|C);

  endmodule

  module alarma_posg(input wire A, B, C, output wire Y4);

    wire notA, notB, notC, w1, w2 , w3, w4, w5;                                 //Creamos nuestros cables

    not (notA, A);
    not (notB, B);
    not (notC, C);

    or  (w1, A, B, C);
    or  (w2, A, B, notC);
    or  (w3, A, notB, C);
    or  (w4, A, notB, notC);
    or  (w5, notA, notB, C);
    and (Y4, w1, w2, w3, w4, w5);

  endmodule

  module alarma_ko(input wire A, B, C, output wire Y5);

    assign Y5 = (A & C) | (A & ~B);

  endmodule

  module alarma_kg(input wire A, B, C, output wire Y6);

    wire notB, w1, w2;

    not (notB, B);

    and (w1, A, C);
    and (w2, A, notB);
    or  (Y6, w1, w2);
  endmodule

LABORATORIO-4/Alarma_carro/ALARMACARRO_tb.v
//ALARMA CARRO
//GABRIEL ALEXANDER FONG PENAGOS
//CARNE 19722
//Modulo TESTEBENCH

module testbench();

  reg AR1, SV1, SM1;                                                            //Creamos los registros para el modulo alarma_sopg
  reg AR11, SV11, SM11;                                                         //Creamos los registros para el modulo alarma_sopo
  reg AR2, SV2, SM2;                                                            //Creamos los registros para el modulo alarma_poso
  reg AR22, SV22, SM22;                                                         //Creamos los registros para el modulo alarma_posg
  reg AR3, SV3, SM3;                                                            //Creamos los registros para el modulo alarma_ko
  reg AR33, SV33, SM33;                                                            //Creamos los registros para el modulo alarma_kp
  wire AL1, AL11, AL2, AL22, AL33, AL3;                                         //Creamos nuestras salidas como wire

  alarma_sopg g1(AR1, SV1, SM1, AL1);
  alarma_sopo op1(AR11, SV11, SM11, AL11);
  alarma_poso op2(AR2, SV2, SM2, AL2);
  alarma_posg g2(AR22, SV22, SM22, AL22);
  alarma_ko   op3(AR3, SV3, SM3, AL3);
  alarma_kg   g3(AR33, SV33, SM33, AL33);

  initial begin                                                                 //INICIAMOS EL MODULO alarma_sopg
    $display("");
    $display(" ALARMA SOP GATELEVELM");
    $display(" AR SV SM | AL1");
    $display("----------|----");
    $monitor("%b  %b  %b | %b", AR1, SV1, SM1, AL1);
       AR1 = 0; SV1 = 0; SM1 = 0;
    #1 AR1 = 0; SV1 = 0; SM1 = 1;
    #1 AR1 = 0; SV1 = 1; SM1 = 0;
    #1 AR1 = 0; SV1 = 1; SM1 = 1;
    #1 AR1 = 1; SV1 = 0; SM1 = 0;
    #1 AR1 = 1; SV1 = 0; SM1 = 1;
    #1 AR1 = 1; SV1 = 1; SM1 = 0;
    #1 AR1 = 1; SV1 = 1; SM1 = 1;

    end

  initial begin                                                                 //INICIAMOS EL MODULO alarma_sopo
  #9
    $display("");
    $display(" ALARMA SOP BM");
    $display(" AR SV SM | AL1");
    $display("----------|----");
    $monitor("%b  %b  %b | %b", AR11, SV11, SM11, AL11);
       AR11 = 0; SV11 = 0; SM11 = 0;
    #1 AR11 = 0; SV11 = 0; SM11 = 1;
    #1 AR11 = 0; SV11 = 1; SM11 = 0;
    #1 AR11 = 0; SV11 = 1; SM11 = 1;
    #1 AR11 = 1; SV11 = 0; SM11 = 0;
    #1 AR11 = 1; SV11 = 0; SM11 = 1;
    #1 AR11 = 1; SV11 = 1; SM11 = 0;
    #1 AR11 = 1; SV11 = 1; SM11 = 1;

      end

  initial begin                                                                 //INICIAMOS EL MODULO alarma_poso
  #17
    $display("");
    $display(" ALARMA POS BM");
    $display(" AR SV SM | AL2");
    $display("----------|----");
    $monitor("%b  %b  %b | %b", AR2, SV2, SM2, AL2);
       AR2 = 0; SV2 = 0; SM2 = 0;
    #1 AR2 = 0; SV2 = 0; SM2 = 1;
    #1 AR2 = 0; SV2 = 1; SM2 = 0;
    #1 AR2 = 0; SV2 = 1; SM2 = 1;
    #1 AR2 = 1; SV2 = 0; SM2 = 0;
    #1 AR2 = 1; SV2 = 0; SM2 = 1;
    #1 AR2 = 1; SV2 = 1; SM2 = 0;
    #1 AR2 = 1; SV2 = 1; SM2 = 1;

      end

    initial begin                                                                 //INICIAMOS EL MODULO alarma_posg
    #25
    $display("");
    $display(" ALARMA POS GATELEVELM");
    $display(" AR SV SM | AL2");
    $display("----------|----");
    $monitor("%b  %b  %b | %b", AR22, SV22, SM22, AL22);
       AR22 = 0; SV22 = 0; SM22 = 0;
    #1 AR22 = 0; SV22 = 0; SM22 = 1;
    #1 AR22 = 0; SV22 = 1; SM22 = 0;
    #1 AR22 = 0; SV22 = 1; SM22 = 1;
    #1 AR22 = 1; SV22 = 0; SM22 = 0;
    #1 AR22 = 1; SV22 = 0; SM22 = 1;
    #1 AR22 = 1; SV22 = 1; SM22 = 0;
    #1 AR22 = 1; SV22 = 1; SM22 = 1;

          end

  initial begin                                                                 //INICIAMOS EL MODULO alarma_ko
  #33
    $display("");
    $display(" ALARMA KARNAUGH BM");
    $display(" AR SV SM | AL3");
    $display("----------|----");
    $monitor("%b  %b  %b | %b", AR3, SV3, SM3, AL3);
       AR3 = 0; SV3 = 0; SM3 = 0;
    #1 AR3 = 0; SV3 = 0; SM3 = 1;
    #1 AR3 = 0; SV3 = 1; SM3 = 0;
    #1 AR3 = 0; SV3 = 1; SM3 = 1;
    #1 AR3 = 1; SV3 = 0; SM3 = 0;
    #1 AR3 = 1; SV3 = 0; SM3 = 1;
    #1 AR3 = 1; SV3 = 1; SM3 = 0;
    #1 AR3 = 1; SV3 = 1; SM3 = 1;

        end

  initial begin                                                                 //INICIAMOS EL MODULO alarma_kg
  #41
    $display("");
    $display(" ALARMA KARNAUGH GATELEVELM");
    $display(" AR SV SM | AL3");
    $display("----------|----");
    $monitor("%b  %b  %b | %b", AR33, SV33, SM33, AL33);
       AR33 = 0; SV33 = 0; SM33 = 0;
    #1 AR33 = 0; SV33 = 0; SM33 = 1;
    #1 AR33 = 0; SV33 = 1; SM33 = 0;
    #1 AR33 = 0; SV33 = 1; SM33 = 1;
    #1 AR33 = 1; SV33 = 0; SM33 = 0;
    #1 AR33 = 1; SV33 = 0; SM33 = 1;
    #1 AR33 = 1; SV33 = 1; SM33 = 0;
    #1 AR33 = 1; SV33 = 1; SM33 = 1;

              end
  initial begin

      $dumpfile("ALARMACARRO_tb.vcd");
      $dumpvars(0, testbench);

  end

endmodule

LABORATORIO-4/Alarma_carro/ACARRO_tb.vcd
$date
	Sat Aug 08 19:25:40 2020
$end
$version
	Icarus Verilog
$end
$timescale
	1ps
$end
$scope module testbench $end
$var wire 1 ! AL1 $end
$var reg 1 " AR1 $end
$var reg 1 # SM1 $end
$var reg 1 $ SV1 $end
$scope module g1 $end
$var wire 1 " A $end
$var wire 1 $ B $end
$var wire 1 # C $end
$var wire 1 ! Y1 $end
$var wire 1 % notA $end
$var wire 1 & notB $end
$var wire 1 ' notC $end
$var wire 1 ( w1 $end
$var wire 1 ) w2 $end
$var wire 1 * w3 $end
$upscope $end
$upscope $end
$enddefinitions $end
#0
$dumpvars
0*
0)
0(
1'
1&
1%
0$
0#
0"
0!
$end
#1
0'
1#
#2
1'
0&
0#
1$
#3
0'
1#
#4
1!
1(
1'
1&
0%
0#
0$
1"
#5
0(
0'
1)
1#
#6
0!
1'
0)
0&
0#
1$
#7
1!
0'
1*
1#
