LABORATORIO-4/Alarma_carro/ALARMACARRO.v
//ALARMA CARRO
//GABRIEL ALEXANDER FONG PENAGOS
//CARNE 19722
//LABORATORIO 04
//EJERCICIO 05 MODULOS 

  module alarma_sopg(input wire A, B, C, output wire Y1);                        //Creamos el modulo de Alarma con configuracion SOP y gate leveling

    wire notA, notB, notC, w1, w2 ,w3;                                          //Creamos nuestros cables
    //Compuertas NOT
    not (notA, A);
    not (notB, B);
    not (notC, C);
    //operaciones
    and (w1, A, notB, notC);
    and (w2, A, notB, C);
    and (w3, A, B, C);
    or  (Y1, w1, w2, w3);

  endmodule                                                                     //Terminamos el modulo alarma_sop

  module alarma_sopo(input wire A, B, C, output wire Y2);                       //Creamos el modulo de Alarma con configuracion SOP y BM

      assign Y2 = (A & ~B & ~C) | (A & ~B & C) | (A & B & C);
  endmodule

  module alarma_poso(input wire A, B, C, output wire Y3);                       //Creamos el modulo de Alarma con configuracion POS y BM

    assign Y3 = (A|B|C) & (A|B|~C) & (A|~B|C) & (A|~B|~C) & (~A|~B|C);

  endmodule

  module alarma_posg(input wire A, B, C, output wire Y4);                       //Creamos el modulo de Alarma con configuracion POS y gate leveling

    wire notA, notB, notC, w1, w2 , w3, w4, w5;                                 //Creamos nuestros cables
    //COMPUERTAS NOY
    not (notA, A);
    not (notB, B);
    not (notC, C);
    //operaciones
    or  (w1, A, B, C);
    or  (w2, A, B, notC);
    or  (w3, A, notB, C);
    or  (w4, A, notB, notC);
    or  (w5, notA, notB, C);
    and (Y4, w1, w2, w3, w4, w5);

  endmodule

  module alarma_ko(input wire A, B, C, output wire Y5);                         //Creamos el modulo de Alarma con configuracion simplificada de KARNAUGH y BM

    assign Y5 = (A & C) | (A & ~B);

  endmodule

  module alarma_kg(input wire A, B, C, output wire Y6);                         //Creamos el modulo de Alarma con configuracion simplificada de KARNAUGH y GATELEVELM

    wire notB, w1, w2;

    not (notB, B);

    and (w1, A, C);
    and (w2, A, notB);
    or  (Y6, w1, w2);
  endmodule

LABORATORIO-4/Alarma_carro/ALARMACARRO_tb.v
//ALARMA CARRO
//GABRIEL ALEXANDER FONG PENAGOS
//CARNE 19722
//Modulo TESTEBENCH

module testbench();

  reg AR1, SV1, SM1;                                                            //Creamos los registros para el modulo alarma_sopg
  reg AR11, SV11, SM11;                                                         //Creamos los registros para el modulo alarma_sopo
  reg AR2, SV2, SM2;                                                            //Creamos los registros para el modulo alarma_poso
  reg AR22, SV22, SM22;                                                         //Creamos los registros para el modulo alarma_posg
  reg AR3, SV3, SM3;                                                            //Creamos los registros para el modulo alarma_ko
  reg AR33, SV33, SM33;                                                          //Creamos los registros para el modulo alarma_kp
  wire AL1, AL11, AL2, AL22, AL33, AL3;                                         //Creamos nuestras salidas como wire

  alarma_sopg g1(AR1, SV1, SM1, AL1);
  alarma_sopo op1(AR11, SV11, SM11, AL11);
  alarma_poso op2(AR2, SV2, SM2, AL2);
  alarma_posg g2(AR22, SV22, SM22, AL22);
  alarma_ko   op3(AR3, SV3, SM3, AL3);
  alarma_kg   g3(AR33, SV33, SM33, AL33);

  initial begin                                                                 //INICIAMOS EL MODULO alarma_sopg
    $display("");
    $display(" ALARMA SOP GATELEVELM");
    $display(" AR SV SM | AL1");
    $display("----------|----");
    $monitor("%b  %b  %b | %b", AR1, SV1, SM1, AL1);
       AR1 = 0; SV1 = 0; SM1 = 0;
    #1 AR1 = 0; SV1 = 0; SM1 = 1;
    #1 AR1 = 0; SV1 = 1; SM1 = 0;
    #1 AR1 = 0; SV1 = 1; SM1 = 1;
    #1 AR1 = 1; SV1 = 0; SM1 = 0;
    #1 AR1 = 1; SV1 = 0; SM1 = 1;
    #1 AR1 = 1; SV1 = 1; SM1 = 0;
    #1 AR1 = 1; SV1 = 1; SM1 = 1;

    end

  initial begin                                                                 //INICIAMOS EL MODULO alarma_sopo
  #9
    $display("");
    $display(" ALARMA SOP BM");
    $display(" AR SV SM | AL1");
    $display("----------|----");
    $monitor("%b  %b  %b | %b", AR11, SV11, SM11, AL11);
       AR11 = 0; SV11 = 0; SM11 = 0;
    #1 AR11 = 0; SV11 = 0; SM11 = 1;
    #1 AR11 = 0; SV11 = 1; SM11 = 0;
    #1 AR11 = 0; SV11 = 1; SM11 = 1;
    #1 AR11 = 1; SV11 = 0; SM11 = 0;
    #1 AR11 = 1; SV11 = 0; SM11 = 1;
    #1 AR11 = 1; SV11 = 1; SM11 = 0;
    #1 AR11 = 1; SV11 = 1; SM11 = 1;

      end

  initial begin                                                                 //INICIAMOS EL MODULO alarma_poso
  #17
    $display("");
    $display(" ALARMA POS BM");
    $display(" AR SV SM | AL2");
    $display("----------|----");
    $monitor("%b  %b  %b | %b", AR2, SV2, SM2, AL2);
       AR2 = 0; SV2 = 0; SM2 = 0;
    #1 AR2 = 0; SV2 = 0; SM2 = 1;
    #1 AR2 = 0; SV2 = 1; SM2 = 0;
    #1 AR2 = 0; SV2 = 1; SM2 = 1;
    #1 AR2 = 1; SV2 = 0; SM2 = 0;
    #1 AR2 = 1; SV2 = 0; SM2 = 1;
    #1 AR2 = 1; SV2 = 1; SM2 = 0;
    #1 AR2 = 1; SV2 = 1; SM2 = 1;

      end

    initial begin                                                                 //INICIAMOS EL MODULO alarma_posg
    #25
    $display("");
    $display(" ALARMA POS GATELEVELM");
    $display(" AR SV SM | AL2");
    $display("----------|----");
    $monitor("%b  %b  %b | %b", AR22, SV22, SM22, AL22);
       AR22 = 0; SV22 = 0; SM22 = 0;
    #1 AR22 = 0; SV22 = 0; SM22 = 1;
    #1 AR22 = 0; SV22 = 1; SM22 = 0;
    #1 AR22 = 0; SV22 = 1; SM22 = 1;
    #1 AR22 = 1; SV22 = 0; SM22 = 0;
    #1 AR22 = 1; SV22 = 0; SM22 = 1;
    #1 AR22 = 1; SV22 = 1; SM22 = 0;
    #1 AR22 = 1; SV22 = 1; SM22 = 1;

          end

  initial begin                                                                 //INICIAMOS EL MODULO alarma_ko
  #33
    $display("");
    $display(" ALARMA KARNAUGH BM");
    $display(" AR SV SM | AL3");
    $display("----------|----");
    $monitor("%b  %b  %b | %b", AR3, SV3, SM3, AL3);
       AR3 = 0; SV3 = 0; SM3 = 0;
    #1 AR3 = 0; SV3 = 0; SM3 = 1;
    #1 AR3 = 0; SV3 = 1; SM3 = 0;
    #1 AR3 = 0; SV3 = 1; SM3 = 1;
    #1 AR3 = 1; SV3 = 0; SM3 = 0;
    #1 AR3 = 1; SV3 = 0; SM3 = 1;
    #1 AR3 = 1; SV3 = 1; SM3 = 0;
    #1 AR3 = 1; SV3 = 1; SM3 = 1;

        end

  initial begin                                                                 //INICIAMOS EL MODULO alarma_kg
  #41
    $display("");
    $display(" ALARMA KARNAUGH GATELEVELM");
    $display(" AR SV SM | AL3");
    $display("----------|----");
    $monitor("%b  %b  %b | %b", AR33, SV33, SM33, AL33);
       AR33 = 0; SV33 = 0; SM33 = 0;
    #1 AR33 = 0; SV33 = 0; SM33 = 1;
    #1 AR33 = 0; SV33 = 1; SM33 = 0;
    #1 AR33 = 0; SV33 = 1; SM33 = 1;
    #1 AR33 = 1; SV33 = 0; SM33 = 0;
    #1 AR33 = 1; SV33 = 0; SM33 = 1;
    #1 AR33 = 1; SV33 = 1; SM33 = 0;
    #1 AR33 = 1; SV33 = 1; SM33 = 1;

              end
  initial begin                                                                 //INICIAMOS PARA COLOCAR NUESTROS DATOS EN GTK WAVE

      $dumpfile("ALARMACARRO_tb.vcd");
      $dumpvars(0, testbench);

  end

endmodule

LABORATORIO-4/Alarma_carro/ALARMACARRO_tb.vcd
$date
	Sun Aug 09 14:49:09 2020
$end
$version
	Icarus Verilog
$end
$timescale
	1ps
$end
$scope module testbench $end
$var wire 1 ! AL33 $end
$var wire 1 " AL3 $end
$var wire 1 # AL22 $end
$var wire 1 $ AL2 $end
$var wire 1 % AL11 $end
$var wire 1 & AL1 $end
$var reg 1 ' AR1 $end
$var reg 1 ( AR11 $end
$var reg 1 ) AR2 $end
$var reg 1 * AR22 $end
$var reg 1 + AR3 $end
$var reg 1 , AR33 $end
$var reg 1 - SM1 $end
$var reg 1 . SM11 $end
$var reg 1 / SM2 $end
$var reg 1 0 SM22 $end
$var reg 1 1 SM3 $end
$var reg 1 2 SM33 $end
$var reg 1 3 SV1 $end
$var reg 1 4 SV11 $end
$var reg 1 5 SV2 $end
$var reg 1 6 SV22 $end
$var reg 1 7 SV3 $end
$var reg 1 8 SV33 $end
$scope module g1 $end
$var wire 1 ' A $end
$var wire 1 3 B $end
$var wire 1 - C $end
$var wire 1 & Y1 $end
$var wire 1 9 notA $end
$var wire 1 : notB $end
$var wire 1 ; notC $end
$var wire 1 < w1 $end
$var wire 1 = w2 $end
$var wire 1 > w3 $end
$upscope $end
$scope module g2 $end
$var wire 1 * A $end
$var wire 1 6 B $end
$var wire 1 0 C $end
$var wire 1 # Y4 $end
$var wire 1 ? notA $end
$var wire 1 @ notB $end
$var wire 1 A notC $end
$var wire 1 B w1 $end
$var wire 1 C w2 $end
$var wire 1 D w3 $end
$var wire 1 E w4 $end
$var wire 1 F w5 $end
$upscope $end
$scope module g3 $end
$var wire 1 , A $end
$var wire 1 8 B $end
$var wire 1 2 C $end
$var wire 1 ! Y6 $end
$var wire 1 G notB $end
$var wire 1 H w1 $end
$var wire 1 I w2 $end
$upscope $end
$scope module op1 $end
$var wire 1 ( A $end
$var wire 1 4 B $end
$var wire 1 . C $end
$var wire 1 % Y2 $end
$upscope $end
$scope module op2 $end
$var wire 1 ) A $end
$var wire 1 5 B $end
$var wire 1 / C $end
$var wire 1 $ Y3 $end
$upscope $end
$scope module op3 $end
$var wire 1 + A $end
$var wire 1 7 B $end
$var wire 1 1 C $end
$var wire 1 " Y5 $end
$upscope $end
$upscope $end
$enddefinitions $end
#0
$dumpvars
xI
xH
xG
xF
xE
xD
xC
xB
xA
x@
x?
0>
0=
0<
1;
1:
19
x8
x7
x6
x5
x4
03
x2
x1
x0
x/
x.
0-
x,
x+
x*
x)
x(
0'
0&
x%
x$
x#
x"
x!
$end
#1
0;
1-
#2
1;
0:
0-
13
#3
0;
1-
#4
1&
1<
1;
1:
09
0-
03
1'
#5
0<
0;
1=
1-
#6
0&
1;
0=
0:
0-
13
#7
1&
0;
1>
1-
#9
0%
0.
04
0(
#10
1.
#11
0.
14
#12
1.
#13
1%
0.
04
1(
#14
1.
#15
0%
0.
14
#16
1%
1.
#17
0$
0/
05
0)
#18
1/
#19
0/
15
#20
1/
#21
1$
0/
05
1)
#22
1/
#23
0$
0/
15
#24
1$
1/
#25
0#
1C
1D
1E
1A
1F
1@
1?
0B
00
06
0*
#26
0#
0C
0A
1B
10
#27
1A
0D
0@
1C
00
16
#28
0#
0E
0A
1D
10
#29
1#
1A
1@
0?
1E
00
06
1*
#30
0A
10
#31
0#
1A
0F
0@
00
16
#32
1#
0A
1F
10
#33
0"
01
07
0+
#34
11
#35
01
17
#36
11
#37
1"
01
07
1+
#38
11
#39
0"
01
17
#40
1"
11
#41
0!
1G
0H
0I
02
08
0,
#42
12
#43
0G
02
18
#44
12
#45
1!
1I
1G
02
08
1,
#46
1H
12
#47
0!
0I
0H
0G
02
18
#48
1!
1H
12
