LABORATORIO-3/TABLA_02POS/tabla_02p.v
//---------------------------
//GABRIEL ALEXANDER FONG PENAGOS
//CARNET 19722
//ELECTRONICA DIGITAL
//LABORATORIO 03
//EJERCICIO TABLA 02 VERSION POS

module tabla_02p();                           //GENERAMOS EL MODULO

  wire w1,w2,w3,w4,w5,nA,nB,nC,sal;           //NOMBRAMOS NUESTROS CABLES QUE SALDRAN DE LAS AND, LAS NEGACIONES DE NUESTRA VARIABLES BINARIAS Y LA SALIDA
  reg A, B, C;                                //NOMBRAMOS NUESTRAS ENTRADAS COMO REGISTROS

//COMPUERTAS

//COMPUERTAS NOT
  not U1(nA,A);
  not U2(nB,B);
  not U3(nC,C);

//COMPUERTAS OR
  or  U4(w1,A,B,C);
  or  U5(w2,A,nB,C);
  or  U6(w3,A,nB,nC);
  or  U7(w4,nA,B,C);
  or  U8(w5,nA,B,nC);

//COMPUERTA AND
  and U9(sal,w1,w2,w3,w4,w5);

  initial begin                                 //INICIAMOS LA SIMULACION
    $display("POS A B C| Y");                   //IMPRIMIMOS EN LA TERMINAL
    $display("---------|");
    $monitor("%b %b %b | %b", A, B, C, sal);      //MUESTRA LOS VALORES DE A B C y LA SALIDA
    A = 0; B = 0; C = 0;                          //CAMBIAMOS LOS VALORES
    #1 A = 0; B = 0; C = 1;                       //COLOCAMOS UN INTERVALO DE TIEMPO PARA CAMBIAR LOS VALORES DE LAS ENTRADAS
    #1 A = 0; B = 1; C = 0;
    #1 A = 0; B = 1; C = 1;
    #1 A = 1; B = 0; C = 0;
    #1 A = 1; B = 0; C = 1;
    #1 A = 1; B = 1; C = 0;
    #1 A = 1; B = 1; C = 1;
    #1 $finish;                                    //FINALIZAMOS LA SIMULACION
  end

  initial                                          //INICIAMOS PARA MOSTRAR LA SIMULACION EN GTK WAVE
    begin
      $dumpfile("tabla_02p_tb.vcd");               //COLOCAMOS LA EXTENSION DEL ARCHIVO _tb Y COLOCAMOS .vcd PARA MOSTRAR EN GTK WAVE
      $dumpvars(0,tabla_02p);                      //TOMAMOS LOS VALORES DEL ARCHIVO
    end

  endmodule                                       //TERMINAMOS EL MODULO

LABORATORIO-3/TABLA_02POS/tabla_02p_tb.vcd
$date
	Fri Jul 31 22:46:27 2020
$end
$version
	Icarus Verilog
$end
$timescale
	1ps
$end
$scope module tabla_02p $end
$var wire 1 ! nA $end
$var wire 1 " nB $end
$var wire 1 # nC $end
$var wire 1 $ sal $end
$var wire 1 % w1 $end
$var wire 1 & w2 $end
$var wire 1 ' w3 $end
$var wire 1 ( w4 $end
$var wire 1 ) w5 $end
$var reg 1 * A $end
$var reg 1 + B $end
$var reg 1 , C $end
$upscope $end
$enddefinitions $end
#0
$dumpvars
0,
0+
0*
1)
1(
1'
1&
0%
0$
1#
1"
1!
$end
#1
1$
1%
0#
1,
#2
0$
0&
1#
0"
0,
1+
#3
0'
1&
0#
1,
#4
1#
1)
0(
1"
1'
0!
0,
0+
1*
#5
0)
1(
0#
1,
#6
1$
1#
1)
0"
0,
1+
#7
0#
1,
