LABORATORIO-8/CODIGO/LAB8.v
//LABORATORIO 8
//ELECTRONICA DIGITAL I
//GABRIEL ALEXANDER FONG PENAGOS 19722

//MODULO CONTADOR
module contador(input wire clk, reset,enable,loads,
                input wire [11:0]LOAD,
                output reg[11:0]CB);

  always @ (posedge clk, posedge reset ) begin //REALIZAMOS UN ALWAYS PARA QUE SE EJECUTE EN TODOO MOMENTO Y CAMBIE EN EL FLANCO DE RELOJ
  if (reset) begin //RESETEA EL VALOR EN 0 LOS 12 BITS
    CB <= 12'b0;
  end
  else if (loads)begin //SI EL LOAD ES 1 COLOCAR EN LA SALIDA EL VALOR PRE-COLOCADO
  CB <= LOAD;
end
else //SI ENABLE ES 1 SUMA 1 EN CADA FLANCO DE RELOJ, SI NO NO SUMA
  if (enable) begin
  CB <= CB + 1;
  end
end
endmodule

//Modulo de lectura de datos de la ROM de 4k X 8
module ROM (input wire [11:0]Addres, // DIRECCION DE 12 BITS
  output wire [7:0]DATO); //TAMAÑO DEL DATO DE 8 BITS

  reg [7:0] MEM[0:4095]; //MEM ES DE TAMAÑO DE 2^12 = 4096 Y CREA EL ARREGLO PARA NUESTROS DATOS
  initial begin         //INICIAMOS LA LECTURA DE NUESTRA LISTA
    $readmemb("Lista.list", MEM);//LEEMOS LOS VALORES DE LA LISTA EN BINARIO
  end
  assign DATO = MEM[Addres]; //LE ASIGANMOS EL VALOR DE MEM EN LA DIRECCION INGRESADA
endmodule // ROM

//MODULO DE ALU DE SALIDA DE 4 BITS
module ALUU(input wire [3:0]A,B,
            input wire [2:0]SEL,
            output reg [3:0]Sal);



  always @ (A,B,SEL) begin //SIEMPRE QUE OCURRA UN CAMBIO EN A B O SEL REALIZARLO EN EL MOMENTO
    case (SEL)            //EL SEL SELECCIONA EL CASE QUE TIENE 8 POSIBLES CASOS DIFERENTES
        3'b000: Sal <= A & B ; //FUNCION  A AND B
        3'b001: Sal <= A | B ; //FUNCION A OR B
        3'b010: Sal <= A + B ; //FUNCION A ADD B
        3'b011: Sal <= Sal ; //,COLOCAMOS TODOO el MISMO VALOR DE ANTES
        3'b100: Sal <= A & (~B) ;//FUNCION A AND ~B
        3'b101: Sal <= A | (~B) ;//FUNCION A OR ~B
        3'b110: Sal <= A - B ;//FUNCION A LESS B
        3'b111: Sal <= (A < B) ? 1:0 ;//FUNCION STL. REALIZA UNA COMPARACION ENTRE A Y B, SI A > B COLOCA 0000, SI A < B COLOCA 0001
      default: Sal <= 4'b0000 ;//POR DEFAULT QUE COLOQUE TODP EN 0
    endcase
  end
endmodule

LABORATORIO-8/CODIGO/LAB8_tb.v
//LABORATORIO 8
//ELECTRONICA DIGITAL I
//GABRIEL ALEXANDER FONG PENAGOS 19722
//TESTBENCH

module testbench();
  reg clk, reset1, enable,loads; //VARIABLES DE ENTRADA DE UN BIT DEL MODULO CONTADOR
  reg [11:0]LOAD; //VALOR DEL LOAD DE 12 BITS QUE LE COLOCAMOS COMO FIJO A LA SALIDA DEL CONTADOR
  wire [11:0]CB; //SALIDA DEL CONTADOR DE 12 BITS

  reg [11:0]Addres; //VARIABLE DE ENTRADA DE 12 BITS PARA EL MODULO ROM
  wire [7:0]DATO;// VARIABLE DE SALIDA DE 7 BITS PARA EL MODULO ROM

  reg [3:0]A,B; //VARIABLE DE ENTRADA PARA EL MODULO ALUU
  reg [2:0]SEL; //VARIABLE DE SELECCION DE LA ALUU
  wire [3:0]OUT;//SALIDA DE LA ALU DE 4 BITS


  contador U1(clk, reset1, enable,loads, LOAD, CB);//MODULO EJERCICIO 1
  ROM U2(Addres, DATO);//MODULO EJERCICIO 2
  ALUU U3(A, B, SEL, OUT);//MODULO EJERCIO 3

  always begin //REALIZAMOS EL RELOJ Y QUE CAMBIE CADA UNIDAD DE TIEMPO
    clk <= 1; #1 clk <= ~clk; #1;
  end


  //REALIZAMOS LAS PRUEBAS DEL MODULO CONTADOR
  initial begin
  reset1 = 1;loads = 0; LOAD = 12'b000000000000; //RESETEAMOS Y LA SEÑAL DEL LOAD APAGADA LE ASIGNAMOS
  #1
  $display("\n");
  $display(" CONTADOR 12 BITS ");
  $display("C \t  R \t E  \t L\t LOAD\t      |\tOUT");
  $monitor("%b \t %b\t %b \t %b \t %b | %b ", clk, reset1, enable,loads, LOAD, CB );
  #1 enable = 1; reset1 = 0; //HABILITAMOS EL ENABLE PARA QUE COMIENCE A CONTAR
  #5 enable = 0;//DESHABILITAMOS ENABLE Y DEJA DE CONTAR
  #3 loads = 1; LOAD = 12'b101010101010; //ENCENDEMOS LA BANDERA DE LOAD Y LE SELECCIONAMOS UN VALOR
  #2 enable = 1;//HABILITAMOS EL ENABLE PARA QUE CUENTE, PERO COMO LOAD SIGUE ENCENDIDO NO CAMBIARA EL VALOR DE SALIDA
  #4 loads = 0;//APAGAMOS LA BANDERA DE LOAD Y SIGUE CONTANDO EN EL VALOR COLOCADO DE LOAD
  #4 loads = 1; LOAD = 12'b101010100000;//VOLVEMOS A HABILITAR LA SEÑAL DE LOAD PERO CON EL ENABLE ENCENDIDO, LOAD TIENE PRIORIDAD SOBRE ENABLE
  #4 loads = 0;//DESHABILITAMOS LA BANDERA DE LOAD Y SIGUE CONTANDO
  #2 enable = 0;// DESHABILITAMOS ENABLE DEJA DE CONTAR
  #1 reset1 = 1;
  end
  //REALIZAMOS LAS PRUEBAS DEL MODULO ROM EN DONDE COLOCAMOS LOS VALORES DEL ADDRESS Y NOS MUESTRA SU VALOR
  initial begin
  #30
  $display("\n");
  $display(" ROM ");
  $display("CLK \t  Addres \t  Dato ");
  $monitor("%b \t %b\t %b ", clk, Addres, DATO);
  Addres = 12'b000000000000;// DIRECCION1 8h00
  #1 Addres = 12'b000000000001; //DIRECCION 2 8h01
  #1 Addres = 12'b000000000010; //DIRECCION 3 8h02
  #1 Addres = 12'b000000000011; //DIRECCION 4 8h03
  #1 Addres = 12'b000000000100; //DIRECCION 5 8h04
  #1 Addres = 12'b000000000111; //DIRECCION 6 8h07
  #1 Addres = 12'b000000001010; //DIRECCION 7 8h10
  #1 Addres = 12'b000000000001; //DIRECCION 8 8h01
  #1 Addres = 12'b000000001000; //DIRECCION 9 8h08
  #1 Addres = 12'b000000010000; //DIRECCION 10 8h16
  #1 Addres = 12'b000000001101; //DIRECCION 11 8h13

  end


//REALIZAMOS LAS PRUEBAS DEL MODULO ALUU Y PROBAMOS TODAS LAS FUNCIONES
  initial begin
  #40
  $display("\n");
  $display(" ALU ");
  $display("CLK \t  A \t B  \t  SEL \tOUT");
  $monitor("%b \t %b\t %b \t %b | %b ", clk, A, B, SEL, OUT );
  A = 4'b1010; B = 4'b0011; SEL = 3'b000; //FUNCION  A AND B
  #1 SEL = 3'b001; //FUNCION A OR B
  #1 SEL = 3'b010; //FUNCION A ADD B
  #1 SEL = 3'b010;//FUNCION A ADD B
  #1 SEL = 3'b011;//ESTA FUNCION NO HACE NADA, COLOCAMOS TODOO el MISMO VALOR DE ANTES
  #1 SEL = 3'b100;//FUNCION A AND ~B
  #1 SEL = 3'b101;//FUNCION A OR ~B
  #1 SEL = 3'b110;//FUNCION A LESS B
  #1 SEL = 3'b111;//FUNCION STL
  #1 A = 4'b010; B = 4'b0011;//POR DEFAULT QUE COLOQUE TODP EN 0
  #2 $finish;
  end

  initial begin                                                                 //INICIAMOS PARA COLOCAR LOS DATOS EN GTK WAVE
        $dumpfile("LAB8_tb.vcd");
        $dumpvars(0, testbench);
      end

endmodule

LABORATORIO-8/CODIGO/LAB8_tb.vcd
$date
	Fri Oct 23 23:42:52 2020
$end
$version
	Icarus Verilog
$end
$timescale
	1ps
$end
$scope module testbench $end
$var wire 4 ! OUT [3:0] $end
$var wire 8 " DATO [7:0] $end
$var wire 12 # CB [11:0] $end
$var reg 4 $ A [3:0] $end
$var reg 12 % Addres [11:0] $end
$var reg 4 & B [3:0] $end
$var reg 12 ' LOAD [11:0] $end
$var reg 3 ( SEL [2:0] $end
$var reg 1 ) clk $end
$var reg 1 * enable $end
$var reg 1 + loads $end
$var reg 1 , reset1 $end
$scope module U1 $end
$var wire 12 - LOAD [11:0] $end
$var wire 1 ) clk $end
$var wire 1 * enable $end
$var wire 1 + loads $end
$var wire 1 , reset $end
$var reg 12 . CB [11:0] $end
$upscope $end
$scope module U2 $end
$var wire 12 / Addres [11:0] $end
$var wire 8 0 DATO [7:0] $end
$upscope $end
$scope module U3 $end
$var wire 4 1 A [3:0] $end
$var wire 4 2 B [3:0] $end
$var wire 3 3 SEL [2:0] $end
$var reg 4 4 Sal [3:0] $end
$upscope $end
$upscope $end
$enddefinitions $end
#0
$dumpvars
bx 4
bx 3
bx 2
bx 1
bx 0
bx /
b0 .
b0 -
1,
0+
x*
1)
bx (
b0 '
bx &
bx %
bx $
b0 #
bx "
bx !
$end
#1
0)
#2
b1 #
b1 .
1)
0,
1*
#3
0)
#4
b10 #
b10 .
1)
#5
0)
#6
b11 #
b11 .
1)
#7
0)
0*
#8
1)
#9
0)
#10
b101010101010 #
b101010101010 .
1)
b101010101010 '
b101010101010 -
1+
#11
0)
#12
1)
1*
#13
0)
#14
1)
#15
0)
#16
b101010101011 #
b101010101011 .
1)
0+
#17
0)
#18
b101010101100 #
b101010101100 .
1)
#19
0)
#20
b101010100000 #
b101010100000 .
1)
b101010100000 '
b101010100000 -
1+
#21
0)
#22
1)
#23
0)
#24
b101010100001 #
b101010100001 .
1)
0+
#25
0)
#26
1)
0*
#27
b0 #
b0 .
0)
1,
#28
1)
#29
0)
#30
1)
b10100000 "
b10100000 0
b0 %
b0 /
#31
0)
b11110001 "
b11110001 0
b1 %
b1 /
#32
1)
b11110 "
b11110 0
b10 %
b10 /
#33
0)
b10001010 "
b10001010 0
b11 %
b11 /
#34
1)
b1000001 "
b1000001 0
b100 %
b100 /
#35
0)
b1 "
b1 0
b111 %
b111 /
#36
1)
b10001111 "
b10001111 0
b1010 %
b1010 /
#37
0)
b11110001 "
b11110001 0
b1 %
b1 /
#38
1)
b11111111 "
b11111111 0
b1000 %
b1000 /
#39
0)
b11000100 "
b11000100 0
b10000 %
b10000 /
#40
b10 !
b10 4
1)
b11100000 "
b11100000 0
b1101 %
b1101 /
b0 (
b0 3
b11 &
b11 2
b1010 $
b1010 1
#41
b1011 !
b1011 4
0)
b1 (
b1 3
#42
b1101 !
b1101 4
1)
b10 (
b10 3
#43
0)
#44
1)
b11 (
b11 3
#45
b1000 !
b1000 4
0)
b100 (
b100 3
#46
b1110 !
b1110 4
1)
b101 (
b101 3
#47
b111 !
b111 4
0)
b110 (
b110 3
#48
b0 !
b0 4
1)
b111 (
b111 3
#49
b1 !
b1 4
0)
b10 $
b10 1
