LABORATORIO-9/CODIGO2/LAB9_2.v
//LABORATORIO 9
//ELECTRONICA DIGITAL I
//GABRIEL ALEXANDER FONG PENAGOS 19722
//EJERCICIO 2

module flipflopD (input wire clk, reset, enable, D,
                  output reg Q);

    always @ ( posedge clk, posedge reset ) begin
      if (reset) begin
        Q <= 1'b0;
      end
      else if (enable) begin //SI EL ENABLE == 1 DEJA PASAR EL VALOR DE D A LA SALIDA Q
        Q <= D;
      end
    end
endmodule // flipflopD

module flipflopT(input wire clk, reset, enable,
                output wire Q);

    wire D;
    not U1(D,Q); // TOMAMOS EL VALOR DE LA SALIDA Y XOR CON 1
    //SE UTILIZO LA XOR POR LA TABLA DE VERDAD, CUANDO EL DATO DE LA ENTRADA ES EL MISMO = 0, DIFERENTES = 1
    flipflopD U1(clk, reset, enable, D, Q);

endmodule

LABORATORIO-9/CODIGO2/LAB9_2_tb.v
//LABORATORIO 9
//ELECTRONICA DIGITAL I
//GABRIEL ALEXANDER FONG PENAGOS 19722
//EJERCICIO 2
//TESTBENCH

module testbench ();

//variables del modulos
reg clk, reset, enable;
wire Q;

flipflopT U1(clk, reset,enable,Q);

always begin //REALIZAMOS EL RELOJ Y QUE CAMBIE CADA UNIDAD DE TIEMPO
  clk <= 1; #1 clk <= ~clk; #1;
end

initial begin
reset = 1;enable= 1;  //RESETEAMOS ENCENDEMOS EL ENABLE Y D = 0
#1
$display("\n");
$display(" FLIP FLOP TOGGLE ");
$display("C \t R \t E  \t | Q");
$monitor("%b \t %b\t %b \t | %b ", clk, reset, enable, Q );
#2 reset = 0; //
#10 enable = 0;
#4 reset = 1;
#2 $finish;
end

initial begin                                                                 //INICIAMOS PARA COLOCAR LOS DATOS EN GTK WAVE
      $dumpfile("LAB9_2_tb.vcd");
      $dumpvars(0, testbench);
    end

endmodule // testbench

LABORATORIO-9/CODIGO2/LAB9_2_tb.vcd
$date
	Fri Oct 30 19:34:20 2020
$end
$version
	Icarus Verilog
$end
$timescale
	1ps
$end
$scope module testbench $end
$var wire 1 ! Q $end
$var reg 1 " clk $end
$var reg 1 # enable $end
$var reg 1 $ reset $end
$scope module U1 $end
$var wire 1 % D $end
$var wire 1 " clk $end
$var wire 1 # enable $end
$var wire 1 $ reset $end
$var wire 1 ! Q $end
$scope module U1 $end
$var wire 1 % D $end
$var wire 1 " clk $end
$var wire 1 # enable $end
$var wire 1 $ reset $end
$var reg 1 ! Q $end
$upscope $end
$upscope $end
$upscope $end
$enddefinitions $end
#0
$dumpvars
1%
1$
1#
1"
0!
$end
#1
0"
#2
1"
#3
0"
0$
#4
0%
1!
1"
#5
0"
#6
1%
0!
1"
#7
0"
#8
0%
1!
1"
#9
0"
#10
1%
0!
1"
#11
0"
#12
0%
1!
1"
#13
0"
0#
#14
1"
#15
0"
#16
1"
#17
1%
0!
0"
1$
