LABORATORIO-4/LAB4/LAB4.v
//GABRIEL ALEXANDER FONG PENAGOS
//CARNE 19722
//ELECTRONICA DIGITAL
//LABORATORIO 04
//EJERCICIO 04 MODULOS

  module gl1_1(input wire A, B, C, output wire Y1);                               //Creamos el modulo para EJERCICIO 1. INCISO 2 EN GATELEVEL
    wire notA, notB, notC, w1, w2, w3;
                                                                                  //Creamos las entradas negadas con la compuerta not
    not (notA, A);
    not (notB, B);
    not (notC, C);
                                                                                  //Realizamos las operaciones con las compuertas para el modulo
    and (w1, A, C);
    and (w2, A, notB);
    and (w3, notA, notC);
    or  (Y1, w1, w2, w3);

    endmodule                                                                     //Terminamos el modulo para el EJERCICIO 1. INCISO 1 EN GATELEVEL


  module gl1_2(input wire A, B, C, output wire Y2);                               // Creamos el modulo para EJERCICIO 1. INCISO 2 EN GATELEVEL

    not(Y2, B);                                                                   //En este modulo solo se necesita negar la entrada B

    endmodule                                                                     //Terminamos el modulo para el EJERCICIO 1. INCISO 2 EN GATELEVEL

  module op1_3(input wire A, B, C, D, output wire Y3);                            // Creamos el modulo para EJERCICIO 1. INCISO 3 EN OPERADORES LÓGICOS

    assign Y3 = (~A & ~B & ~C & ~D) | (~A & ~B & C & D) | (~A & B & ~C & D) | (~A & B & C & ~D) | (A & B & ~C & ~D) | (A & B & C & D) | (A & ~B & ~C & D) | (A & ~B & C & ~D);

  endmodule

  module op1_4(input wire A, B, C, D, output wire Y4);                           //Creamos el modulo para EJERCICIO 1. INCISO 4 EN OPERADORES LÓGICOS

    assign Y4 = (A & B) | (A & ~C & ~D) | (A & C & D);

  endmodule

  module op2_1(input wire A, B, C, D, output wire Y5);                          //Creamos el modulo para EJERCICIO 2. INCISO 1 EN OPERADORES LÓGICOS

    assign Y5 = (A & ~C) | (~B & ~C & ~D) | (A & ~D) | (A & ~B);

  endmodule

  module gl2_2(input wire A, B, C, output wire Y6);                              //Creamos el modulo para EJERCICIO 1. INCISO 2 EN GATELEVEL

    wire notB;

    not (notB, B);
    or  (Y6, notB, C);

  endmodule

  module op2_3(input wire A, B, C, D, output wire Y7);                          //Creamos el modulo para EJERCICIO 2. INCISO 3 EN OPERADORES LÓGICOS

    assign Y7 = B | (~C & D) | (A & D);

  endmodule

  module gl2_4(input wire A, B, C, output wire Y8);                             //Creamos el modulo para EJERCICIO 2. INCISO 3 EN GATELEVEL

    wire notA, notC, w1;

    not (notA, A);
    not (notC, C);
    and (w1, notA, notC);
    or  (Y8, w1, B);

  endmodule

LABORATORIO-4/LAB4/LAB4_tb.v
//GABRIEL ALEXANDER FONG PENAGOS
//CARNE 19722
//LABORATORIO 04

module testbench();

  reg in1A, in1B, in1C;                                                         //REGISTROS DEL MODULO gl1_1
  reg in2A, in2B, in2C;                                                         //REGISTROS DEL MODULO gl1_2
  reg in3A, in3B, in3C, in3D;                                                   //REGISTROS DEL MODULO op1_3
  reg in4A, in4B, in4C, in4D;                                                   //REGISTROS DEL MODULO op1_4
  reg in5A, in5B, in5C, in5D;                                                   //REGISTROS DEL MODULO op1_4
  reg in6A, in6B, in6C;                                                         //REGISTROS DEL MODULO op1_4
  reg in7A, in7B, in7C, in7D;                                                   //REGISTROS DEL MODULO op1_4
  reg in8A, in8B, in8C;                                                   //REGISTROS DEL MODULO op1_4

  wire out1, out2, out3, out4, out5, out6, out7, out8;

  gl1_1 G1(in1A, in1B, in1C, out1);                                             //NOMBRAMOS EL MODULO Y ADENTRO COLOCAMOS LAS ENTRADSDAS Y SALIDAS A UTILIZAR
  gl1_2 G2(in2A, in2B, in2C, out2);
  op1_3 OP3(in3A, in3B, in3C, in3D, out3);
  op1_4 OP4(in4A, in4B, in4C, in4D, out4);
  op2_1 OP5(in5A, in5B, in5C, in5D, out5);
  gl2_2 G6(in6A, in6B, in6C, out6);
  op2_3 OP7(in7A, in7B, in7C, in7D, out7);
  gl2_4 G8(in8A, in8B, in8C, out8);

  initial begin                                                                 //INICIAMOS EL MODULO gl1_1
    $display(" EJERCICIO 1 TABLA 1");
    $display(" A B C | Y1");
    $display("-------|----");
    $monitor("%b %b %b | %b", in1A, in1B, in1C, out1);
       in1A = 0; in1B = 0; in1C = 0;
    #1 in1A = 0; in1B = 0; in1C = 1;
    #1 in1A = 0; in1B = 1; in1C = 0;
    #1 in1A = 0; in1B = 1; in1C = 1;
    #1 in1A = 1; in1B = 0; in1C = 0;
    #1 in1A = 1; in1B = 0; in1C = 1;
    #1 in1A = 1; in1B = 1; in1C = 0;
    #1 in1A = 1; in1B = 1; in1C = 1;

    end

    initial begin                                                               //
    #9
    $display(" EJERCICIO 1 TABLA 2");
    $display(" A B C | Y2");
    $display("-------|----");
    $monitor("%b %b %b | %b", in2A, in2B, in2C, out2);
       in2A = 0; in2B = 0; in2C = 0;
    #1 in2A = 0; in2B = 0; in2C = 1;
    #1 in2A = 0; in2B = 1; in2C = 0;
    #1 in2A = 0; in2B = 1; in2C = 1;
    #1 in2A = 1; in2B = 0; in2C = 0;
    #1 in2A = 1; in2B = 0; in2C = 1;
    #1 in2A = 1; in2B = 1; in2C = 0;
    #1 in2A = 1; in2B = 1; in2C = 1;

    end

    initial begin
    #17
    $display(" EJERCICIO 1 TABLA 3");
    $display(" A B C D | Y3");
    $display("---------|----");
    $monitor("%b %b %b %b | %b", in3A, in3B, in3C, in3D, out3);
       in3A = 0; in3B = 0; in3C = 0; in3D = 0;
    #1 in3A = 0; in3B = 0; in3C = 0; in3D = 1;
    #1 in3A = 0; in3B = 0; in3C = 1; in3D = 0;
    #1 in3A = 0; in3B = 0; in3C = 1; in3D = 1;
    #1 in3A = 0; in3B = 1; in3C = 0; in3D = 0;
    #1 in3A = 0; in3B = 1; in3C = 0; in3D = 1;
    #1 in3A = 0; in3B = 1; in3C = 1; in3D = 0;
    #1 in3A = 0; in3B = 1; in3C = 1; in3D = 1;
    #1 in3A = 1; in3B = 0; in3C = 0; in3D = 0;
    #1 in3A = 1; in3B = 0; in3C = 0; in3D = 1;
    #1 in3A = 1; in3B = 0; in3C = 1; in3D = 0;
    #1 in3A = 1; in3B = 0; in3C = 1; in3D = 1;
    #1 in3A = 1; in3B = 1; in3C = 0; in3D = 0;
    #1 in3A = 1; in3B = 1; in3C = 0; in3D = 1;
    #1 in3A = 1; in3B = 1; in3C = 1; in3D = 0;
    #1 in3A = 1; in3B = 1; in3C = 1; in3D = 1;

    end

    initial begin
    #33
    $display(" EJERCICIO 1 TABLA 4");
    $display(" A B C D | Y4");
    $display("---------|----");
    $monitor("%b %b %b %b | %b", in4A, in4B, in4C, in4D, out4);
       in4A = 0; in4B = 0; in4C = 0; in4D = 0;
    #1 in4A = 0; in4B = 0; in4C = 0; in4D = 1;
    #1 in4A = 0; in4B = 0; in4C = 1; in4D = 0;
    #1 in4A = 0; in4B = 0; in4C = 1; in4D = 1;
    #1 in4A = 0; in4B = 1; in4C = 0; in4D = 0;
    #1 in4A = 0; in4B = 1; in4C = 0; in4D = 1;
    #1 in4A = 0; in4B = 1; in4C = 1; in4D = 0;
    #1 in4A = 0; in4B = 1; in4C = 1; in4D = 1;
    #1 in4A = 1; in4B = 0; in4C = 0; in4D = 0;
    #1 in4A = 1; in4B = 0; in4C = 0; in4D = 1;
    #1 in4A = 1; in4B = 0; in4C = 1; in4D = 0;
    #1 in4A = 1; in4B = 0; in4C = 1; in4D = 1;
    #1 in4A = 1; in4B = 1; in4C = 0; in4D = 0;
    #1 in4A = 1; in4B = 1; in4C = 0; in4D = 1;
    #1 in4A = 1; in4B = 1; in4C = 1; in4D = 0;
    #1 in4A = 1; in4B = 1; in4C = 1; in4D = 1;

    end
    initial begin
    #49
    $display(" EJERCICIO 2 TABLA 1");
    $display(" A B C D | Y5");
    $display("---------|----");
    $monitor("%b %b %b %b | %b", in5A, in5B, in5C, in5D, out5);
       in5A = 0; in5B = 0; in5C = 0; in5D = 0;
    #1 in5A = 0; in5B = 0; in5C = 0; in5D = 1;
    #1 in5A = 0; in5B = 0; in5C = 1; in5D = 0;
    #1 in5A = 0; in5B = 0; in5C = 1; in5D = 1;
    #1 in5A = 0; in5B = 1; in5C = 0; in5D = 0;
    #1 in5A = 0; in5B = 1; in5C = 0; in5D = 1;
    #1 in5A = 0; in5B = 1; in5C = 1; in5D = 0;
    #1 in5A = 0; in5B = 1; in5C = 1; in5D = 1;
    #1 in5A = 1; in5B = 0; in5C = 0; in5D = 0;
    #1 in5A = 1; in5B = 0; in5C = 0; in5D = 1;
    #1 in5A = 1; in5B = 0; in5C = 1; in5D = 0;
    #1 in5A = 1; in5B = 0; in5C = 1; in5D = 1;
    #1 in5A = 1; in5B = 1; in5C = 0; in5D = 0;
    #1 in5A = 1; in5B = 1; in5C = 0; in5D = 1;
    #1 in5A = 1; in5B = 1; in5C = 1; in5D = 0;
    #1 in5A = 1; in5B = 1; in5C = 1; in5D = 1;

    end

    initial begin                                                               //
    #57
    $display(" EJERCICIO 2 TABLA 2");
    $display(" A B C | Y6");
    $display("-------|----");
    $monitor("%b %b %b | %b", in6A, in6B, in6C, out6);
       in6A = 0; in6B = 0; in6C = 0;
    #1 in6A = 0; in6B = 0; in6C = 1;
    #1 in6A = 0; in6B = 1; in6C = 0;
    #1 in6A = 0; in6B = 1; in6C = 1;
    #1 in6A = 1; in6B = 0; in6C = 0;
    #1 in6A = 1; in6B = 0; in6C = 1;
    #1 in6A = 1; in6B = 1; in6C = 0;
    #1 in6A = 1; in6B = 1; in6C = 1;

    end

    initial begin                                                               //
    #65
    $display(" EJERCICIO 2 TABLA 3");
    $display(" A B C D | Y7");
    $display("---------|----");
    $monitor("%b %b %b %b | %b", in7A, in7B, in7C, in7D, out7);
       in7A = 0; in7B = 0; in7C = 0; in7D = 0;
    #1 in7A = 0; in7B = 0; in7C = 0; in7D = 1;
    #1 in7A = 0; in7B = 0; in7C = 1; in7D = 0;
    #1 in7A = 0; in7B = 0; in7C = 1; in7D = 1;
    #1 in7A = 0; in7B = 1; in7C = 0; in7D = 0;
    #1 in7A = 0; in7B = 1; in7C = 0; in7D = 1;
    #1 in7A = 0; in7B = 1; in7C = 1; in7D = 0;
    #1 in7A = 0; in7B = 1; in7C = 1; in7D = 1;
    #1 in7A = 1; in7B = 0; in7C = 0; in7D = 0;
    #1 in7A = 1; in7B = 0; in7C = 0; in7D = 1;
    #1 in7A = 1; in7B = 0; in7C = 1; in7D = 0;
    #1 in7A = 1; in7B = 0; in7C = 1; in7D = 1;
    #1 in7A = 1; in7B = 1; in7C = 0; in7D = 0;
    #1 in7A = 1; in7B = 1; in7C = 0; in7D = 1;
    #1 in7A = 1; in7B = 1; in7C = 1; in7D = 0;
    #1 in7A = 1; in7B = 1; in7C = 1; in7D = 1;

    end

    initial begin
    #81                                                              //INICIAMOS EL MODULO gl1_1
      $display(" EJERCICIO 2 TABLA 4");
      $display(" A B C | Y8");
      $display("-------|----");
      $monitor("%b %b %b | %b", in8A, in8B, in8C, out8);
        in8A = 0; in8B = 0; in8C = 0;
     #1 in8A = 0; in8B = 0; in8C = 1;
     #1 in8A = 0; in8B = 1; in8C = 0;
     #1 in8A = 0; in8B = 1; in8C = 1;
     #1 in8A = 1; in8B = 0; in8C = 0;
     #1 in8A = 1; in8B = 0; in8C = 1;
     #1 in8A = 1; in8B = 1; in8C = 0;
     #1 in8A = 1; in8B = 1; in8C = 1;

      end

    initial begin

      $dumpfile("LAB4_tb.vcd");
      $dumpvars(0, testbench);

    end

  endmodule

LABORATORIO-4/LAB4/LAB4_tb.vcd
$date
	Sun Aug 09 10:25:17 2020
$end
$version
	Icarus Verilog
$end
$timescale
	1ps
$end
$scope module testbench $end
$var wire 1 ! out8 $end
$var wire 1 " out7 $end
$var wire 1 # out6 $end
$var wire 1 $ out5 $end
$var wire 1 % out4 $end
$var wire 1 & out3 $end
$var wire 1 ' out2 $end
$var wire 1 ( out1 $end
$var reg 1 ) in1A $end
$var reg 1 * in1B $end
$var reg 1 + in1C $end
$var reg 1 , in2A $end
$var reg 1 - in2B $end
$var reg 1 . in2C $end
$var reg 1 / in3A $end
$var reg 1 0 in3B $end
$var reg 1 1 in3C $end
$var reg 1 2 in3D $end
$var reg 1 3 in4A $end
$var reg 1 4 in4B $end
$var reg 1 5 in4C $end
$var reg 1 6 in4D $end
$var reg 1 7 in5A $end
$var reg 1 8 in5B $end
$var reg 1 9 in5C $end
$var reg 1 : in5D $end
$var reg 1 ; in6A $end
$var reg 1 < in6B $end
$var reg 1 = in6C $end
$var reg 1 > in7A $end
$var reg 1 ? in7B $end
$var reg 1 @ in7C $end
$var reg 1 A in7D $end
$var reg 1 B in8A $end
$var reg 1 C in8B $end
$var reg 1 D in8C $end
$scope module G1 $end
$var wire 1 ) A $end
$var wire 1 * B $end
$var wire 1 + C $end
$var wire 1 ( Y1 $end
$var wire 1 E notA $end
$var wire 1 F notB $end
$var wire 1 G notC $end
$var wire 1 H w1 $end
$var wire 1 I w2 $end
$var wire 1 J w3 $end
$upscope $end
$scope module G2 $end
$var wire 1 , A $end
$var wire 1 - B $end
$var wire 1 . C $end
$var wire 1 ' Y2 $end
$upscope $end
$scope module G6 $end
$var wire 1 ; A $end
$var wire 1 < B $end
$var wire 1 = C $end
$var wire 1 # Y6 $end
$var wire 1 K notB $end
$upscope $end
$scope module G8 $end
$var wire 1 B A $end
$var wire 1 C B $end
$var wire 1 D C $end
$var wire 1 ! Y8 $end
$var wire 1 L notA $end
$var wire 1 M notC $end
$var wire 1 N w1 $end
$upscope $end
$scope module OP3 $end
$var wire 1 / A $end
$var wire 1 0 B $end
$var wire 1 1 C $end
$var wire 1 2 D $end
$var wire 1 & Y3 $end
$upscope $end
$scope module OP4 $end
$var wire 1 3 A $end
$var wire 1 4 B $end
$var wire 1 5 C $end
$var wire 1 6 D $end
$var wire 1 % Y4 $end
$upscope $end
$scope module OP5 $end
$var wire 1 7 A $end
$var wire 1 8 B $end
$var wire 1 9 C $end
$var wire 1 : D $end
$var wire 1 $ Y5 $end
$upscope $end
$scope module OP7 $end
$var wire 1 > A $end
$var wire 1 ? B $end
$var wire 1 @ C $end
$var wire 1 A D $end
$var wire 1 " Y7 $end
$upscope $end
$upscope $end
$enddefinitions $end
#0
$dumpvars
xN
xM
xL
xK
1J
0I
0H
1G
1F
1E
xD
xC
xB
xA
x@
x?
x>
x=
x<
x;
x:
x9
x8
x7
x6
x5
x4
x3
x2
x1
x0
x/
x.
x-
x,
0+
0*
0)
1(
x'
x&
x%
x$
x#
x"
x!
$end
#1
0(
0J
0G
1+
#2
1(
1J
1G
0F
0+
1*
#3
0(
0J
0G
1+
#4
1(
1I
1G
1F
0E
0+
0*
1)
#5
0G
1H
1+
#6
0(
0I
1G
0H
0F
0+
1*
#7
1(
0G
1H
1+
#9
1'
0.
0-
0,
#10
1.
#11
0'
0.
1-
#12
1.
#13
1'
0.
0-
1,
#14
1.
#15
0'
0.
1-
#16
1.
#17
1&
02
01
00
0/
#18
0&
12
#19
02
11
#20
1&
12
#21
0&
02
01
10
#22
1&
12
#23
02
11
#24
0&
12
#25
02
01
00
1/
#26
1&
12
#27
02
11
#28
0&
12
#29
1&
02
01
10
#30
0&
12
#31
02
11
#32
1&
12
#33
0%
06
05
04
03
#34
16
#35
06
15
#36
16
#37
06
05
14
#38
16
#39
06
15
#40
16
#41
1%
06
05
04
13
#42
0%
16
#43
06
15
#44
1%
16
#45
06
05
14
#46
16
#47
06
15
#48
16
#49
1$
0:
09
08
07
#50
0$
1:
#51
0:
19
#52
1:
#53
0:
09
18
#54
1:
#55
0:
19
#56
1:
#57
1$
0:
09
08
17
#58
1:
#59
0:
19
#60
1:
#61
1$
0:
09
18
#62
1:
#63
0:
19
#64
0$
1:
#65
1#
1K
0=
0<
0;
#66
1=
#67
0#
0K
0=
1<
#68
1#
1=
#69
1K
0=
0<
1;
#70
1=
#71
0#
0K
0=
1<
#72
1#
1=
#73
0"
0A
0@
0?
0>
#74
1"
1A
#75
0"
0A
1@
#76
1A
#77
1"
0A
0@
1?
#78
1A
#79
0A
1@
#80
1A
#81
0"
0A
0@
0?
1>
#82
1"
1A
#83
0"
0A
1@
#84
1"
1A
#85
0A
0@
1?
#86
1A
#87
0A
1@
#88
1A
#89
1!
1N
1M
1L
0D
0C
0B
#90
0!
0N
0M
1D
#91
1N
1M
1!
0D
1C
#92
0N
0M
1D
#93
1M
0!
0L
0D
0C
1B
#94
0M
1D
#95
1M
1!
0D
1C
#96
0M
1D
